Workbook
Name ARCHITECT: '[1]Load Sheet'!$D$11
Name ARPEF: '[2]CAT - CODE'!$G$1524
Name BF: '[2]CAT - CODE'!$G$1528
Name BIDDATE: '[1]Load Sheet'!$D$10
Name BLDAREA: '[1]Load Sheet'!$D$12
Name BUDGET_DATA: '[3]Budget Tracker'!$AK$6:$CX$116
Name BUDGET_STATUS: '[3]Budget Tracker'!$AK$5:$CX$5
Name BUDGET_TITLE_FY: '[3]Budget Tracker'!$AK$4:$CX$4
Name BUDGET_TITLE_MONTH: '[3]Budget Tracker'!$AK$2:$CX$2
Name BUDGET_TITLE_QUARTER: '[3]Budget Tracker'!$AK$3:$CX$3
Name CB_Precast: '[4]Option 1.2A'!$J$19:$L$21
Name CB_Procurement: '[4]Option 1.2A'!$N$50:$N$69
Name cb_sChart10D6460A_opts: "1, 1, 1, False, 2, True, False, , 0, False, False, 1, 1"
Name cb_sChart10D65256_opts: "1, 1, 1, False, 2, True, False, , 0, False, False, 1, 1"
Name cb_sChart10D653EB_opts: "1, 1, 1, False, 2, True, False, , 0, False, False, 1, 1"
Name cb_sChart10D65893_opts: "1, 1, 1, False, 2, True, False, , 0, False, False, 1, 1"
Name cb_sChart12595BBC_opts: "1, 1, 1, False, 2, True, False, , 0, False, False, 2, 2"
Name cb_sChart12595E44_opts: "1, 3, 1, False, 2, True, False, , 0, True, False, 2, 2"
Name cb_sChartEE4CE1B_opts: "1, 4, 1, False, 2, False, False, , 0, False, False, 1, 1"
Name cb_sChartEE4CF99_opts: "1, 1, 1, False, 2, False, False, , 0, False, False, 1, 1"
Name cb_sChartEE4DD06_opts: "1, 1, 1, False, 2, False, False, , 0, False, False, 1, 2"
Name cb_sChartEE4E93B_opts: "1, 1, 1, False, 2, False, False, , 0, False, False, 1, 1"
Name cb_sChartEE51E95_opts: "1, 1, 1, False, 2, False, False, , 0, False, False, 1, 1"
Name cb_sChartEED7645_opts: "1, 1, 1, False, 2, False, False, , 0, False, False, 1, 1"
Name cb_sChartEEDA195_opts: "1, 1, 1, False, 2, False, False, , 0, False, False, 1, 1"
Name cb_sChartEEDC338_opts: "1, 1, 1, False, 2, False, False, , 0, False, False, 1, 1"
Name cb_sChartEEDEDB8_opts: "1, 1, 1, False, 2, False, False, , 0, False, True, 1, 1"
Name cb_sChartEEDEE5A_opts: "1, 3, 1, False, 2, True, False, , 0, False, True, 1, 1"
Name cb_sChartEEDF178_opts: "1, 3, 1, False, 2, False, False, , 0, False, True, 1, 1"
Name cb_sChartF6A6B11_opts: "1, 1, 1, False, 2, True, False, , 0, False, False, 1, 1"
Name cb_sChartFD191DC_opts: "1, 3, 1, False, 2, True, False, , 0, False, True, 1, 1"
Name cb_sChartFD1A245_opts: "1, 3, 1, False, 2, True, False, , 0, False, True, 1, 1"
Name cb_sChartFD3F0E9_opts: "1, 3, 1, False, 2, True, False, , 0, False, False, 1, 1"
Name cb_sChartFD3F27E_opts: "1, 3, 1, False, 2, True, False, , 0, False, True, 1, 1"
Name cb_sChartFD58483_opts: "1, 1, 1, False, 2, True, False, , 0, False, False, 1, 1"
Name cb_sChartFD5C4CD_opts: "1, 1, 1, False, 2, True, False, , 0, False, False, 1, 1"
Name cb_sChartFD5D4CE_opts: "1, 1, 1, False, 2, True, False, , 0, False, False, 1, 1"
Name cb_sChartFD5DF34_opts: "1, 1, 1, False, 2, True, False, , 0, False, False, 1, 1"
Name cb_sChartFD5EFC0_opts: "1, 1, 1, False, 2, True, False, , 0, False, False, 1, 1"
Name cb_sChartFD5FDB9_opts: "1, 1, 1, False, 2, True, False, , 0, False, False, 1, 1"
Name cb_sChartFE54712_opts: "1, 3, 1, False, 2, True, False, , 0, False, True, 1, 1"
Name CB_Screw: '[4]Option 1.2A'!$M$19:$P$21
Name CIPEF: '[2]CAT - CODE'!$G$1517
Name CLEARHEIGHT: '[1]Load Sheet'!$D$13
Name CODE_PREFIX_L3_E: '[3]Package Register'!$AO$217:$AO$325+'[3]Package Register'!$AO$217:$AO$360
Name COMPANY_NO: OFFSET('[5]Proj Input'!$B$4,0,0,COUNTA('[5]Proj Input'!$B$4:$B$13),1)
Name COPEF: '[2]CAT - CODE'!$G$1516
Name CorrespondingList: OFFSET(INDIRECT(ADDRESS(MATCH(Val1Cell,Objects,0)+112,2,,,"PCO")),0,0,COUNTIF(Objects,Val1Cell),1)
Name CorrespondingList: OFFSET(INDIRECT(ADDRESS(MATCH(Val1Cell,Objects,0)+112,2,,,"PCO")),0,0,COUNTIF(Objects,Val1Cell),1)
Name CorrespondingList: OFFSET(INDIRECT(ADDRESS(MATCH(Val1Cell,Objects,0)+112,2,,,"PCO")),0,0,COUNTIF(Objects,Val1Cell),1)
Name CorrespondingList2: OFFSET(INDIRECT(ADDRESS(MATCH(Val1Cell,Objects,0)+112,2,,,"PCO")),0,0,COUNTIF(Objects,Val1Cell),1)
Name CorrespondingList2: OFFSET(INDIRECT(ADDRESS(MATCH(Val1Cell,Objects,0)+112,2,,,"PCO")),0,0,COUNTIF(Objects,Val1Cell),1)
Name CorrespondingList2: OFFSET(INDIRECT(ADDRESS(MATCH(Val1Cell,Objects,0)+112,2,,,"PCO")),0,0,COUNTIF(Objects,Val1Cell),1)
Name CREW_TABLE: [6]INFO!$B$13:$G$60
Name CURRENCY: [6]INFO!$C$4:$E$10
Name CURRENCY2: [6]INFO!$C$4:$E$10
Name DCLABSTOT: 24738790
Name DCLABTOT: 27763421
Name DCMATLCTOT: 1233848
Name DCMATLTOT: 11167072

Sheet Preface
B12: Doc Ref | C12: 855DC-1540-MX-IT-0006
B14: Title | C14: Decarb Green Systems (DGS) Delphi Interface Requirements Verification and Acceptance Matrix (RVAM)
B15: Author | C15: Neil Hall | E15: Position | F15: Systems Engineer | H15: Department | I15: Decarb Systems Delivery
B16: Reviewers | C16: Abby Buters | E16: Position | F16: Green Systems Development Manager | H16: Department | I16: Green Systems Program
C17: Mark Mennell | E17: Position | F17: Principal Software Engineer | H17: Department | I17: Green Systems Program
C18: Andrew Malcolm | E18: Position | F18: Head of Green Systems | H18: Department | I18: Green Systems Program
B21: Purpose
B22: This interface requirements verification and acceptance matrix (RVAM) is developed to provide the Decarb Green Systems programme with a structured, traceable method for capturing, reviewing, and refining interface requirements before they are entered into the requirements repository. This tool is intended to support requirements gathering and engineering during the early stages of system definition and requirements specification. It allows engineers, managers, and stakeholders to record draft requirements derived from the system architecture and interface register and to conduct initial reviews for clarity, completeness, and consistency.
B24: About Requirements Engineering
B25: Requirements engineering is a structured approach focused on defining, analysing, documenting, verifying and validating the needs and constraints that stakeholders require a system to meet. It ensures that all functions, interfaces, and performance expectations are understood and agreed upon before design and implementation begin. Practical requirements engineering reduces project risks, supports traceability throughout the system lifecycle, and enhances verification and validation outcomes.
B27: Intended Use
B28: The RVAM should be used collaboratively by program and project teams and subject matter experts to: - Capture candidate requirements in a consistent, reviewable format. - Record comments, review status, and actions from requirements review sessions. - Identify dependencies and interfaces between requirements. - Prepare clean, validated inputs for capture into the requirements repository. - Provide a mature and traceable set of baseline interface requirements aligned to systems engineering best practice (ISO/IEC 15288).
B30: Scope
B31: This RVAM is intended solely for the initial capture and review of interface requirements before they are imported into the requirements repository. The scope of this template is limited to identifying, reviewing, and documenting requirements in all lifecycle phases. It should be used to capture verification results, validation methods, evidence, and change management records throughout the lifecycle of the requirements.
B33: Table Field Definitions
B34: Field | D34: Definition / Purpose
B35: Req ID | D35: A unique identifier assigned to each requirement for traceability and reference. This ID remains consistent through the RMS import and lifecycle.
B36: Requirement Text | D36: The full, precise statement of the requirement, written in clear and testable language that defines what the system or subsystem must achieve.
B37: Artifact Type | D37: The classification of the requirement according to its nature, such as System, Subsystem, Functional, Interface, etc.
B38: Source | D38: The origin of the requirement, such as a stakeholder document, standard, contract clause, system specification, or engineering analysis.
B39: Rationale | D39: The reason the requirement exists, describing the intent or justification (e.g. regulatory compliance, operational need, safety objective).
B40: Criticality Level | D40: An assessment of the requirement’s importance or impact on the system performance, safety, or compliance (e.g. High, Medium, Low, Very Low).
B41: Quality Flaw | D41: Notes identifying any issues or ambiguities in the requirement text, such as incomplete, unverifiable, or unclear wording, to guide re-drafting.
B42: Review Notes | D42: Comments and observations made during the review process, including recommended actions, clarifications, or cross-references.
B43: Discipline | D43: The engineering or functional area responsible for or affected by the requirement.
B44: WBS L1 / L2 / L3 | D44: References to the corresponding levels of the Work Breakdown Structure (WBS) to align each requirement with its relevant project scope element. These support hierarchical traceability from program level to subsystem.
B45: Facility Code | D45: WBS numeric identifier for to support hierarchical traceability from program level to subsystem.
... B49: Verification Method | D49: The intended means by which the requirement will be verified once implemented. Typical categories include Analysis, Inspection, Test, or Demonstration.
B51: Requirement Type Definitions
B52: Requirement Type | D52: Definition
B53: Business Requirement | D53: A high-level need or objective that reflects what the organisation is trying to achieve. It expresses business outcomes, value drivers, or strategic goals rather than technical solutions.
B54: Functional Requirement | D54: A description of what a system, component, or process must do. It defines behaviours, actions, inputs, outputs, and rules required to achieve a capability.
B55: System Requirement | D55: A requirement allocated to the system as a whole, defining the performance, behaviour, constraints, or characteristics the system must meet. System requirements sit above subsystem-level detail.
B56: Project/Subsystem Requirement | D56: A requirement specific to an individual subsystem or project component. It refines system-level requirements into implementable expectations for a defined part of the solution.
B57: Interface Requirement | D57: A requirement describing how two systems, subsystems, components, or organisations interact. It specifies data, commands, physical connections, timing, protocols, and responsibilities at system boundaries.
B58: Scope Requirement | D58: A requirement that defines what is included or excluded from the project, system, or design boundary. It clarifies limits, assumptions, and expectations to control scope and prevent ambiguity.
B59: Technical Requirement | D59: A requirement specifying a technical constraint or characteristic, such as performance metrics, capacity, standards compliance, environmental conditions, safety margins, or engineering rules.
B60: Process Requirement | D60: A requirement describing how an activity must be conducted. It defines procedural steps, workflows, responsibilities, or governance needed to deliver or operate the system.
B61: Information | D61: Content provided for context, explanation, or clarification that does not represent a requirement and does not impose obligations on the solution.
B62: Heading | D62: A structural label used to group or organise requirements. It is not itself a requirement.
B63: Other | D63: A placeholder category for items that do not clearly fit into the defined requirement types and require further classification or review.

Sheet Document Control 
B13: Revision | C13: Date | E13: Author | G13: Revision Desciption
B14: A | C14: 46007 | E14: Neil Hall | G14: First draft of Delphi interface requirements for review. Requirement are derived from the Decarb Green Systems Architecture. Link to the system architecture: https://fortescue-dgs.netlify.app
B15: B | C15: 16/01/2026 | E15: Neil Hall, Sam Gould | G15: Revised the document preface. Updated to fix inaccuracies in the interface description and to include stakeholder review feedback.

Sheet Requirements
A1: Req ID | B1: Lvl | C1: Requirement Text | D1: Artifact Type | E1: Source | F1: Apportionment | G1: Rationale | H1: Supporting Information from Interface Register | I1: Criticality Level | J1: Quality Flaw | K1: Verification Method | L1: Validation Method | M1: Requirement Status
A2: GSP-RH-0001 | B2: 1 | C2: Green Systems Interface Requirements | D2: Heading | M2: N/A
A3: GSP-RH-0002 | B3: 2 | C3: Delphi Interface Requirements | D3: Heading | M3: N/A
A4: GSP-IR-0003 | C4: The interface shall provide Heavy Mining Equipment (HME) operational and load-profile input data to Delphi at a frequency of 1 Hz (one update per second), with a maximum end-to-end latency of up to 2 seconds, to support fleet simulation and energy feasibility analysis. | D4: Interface Requirement | E4: Green Systems Interface Register, Interface DGS-I_0023 | F4: Delphi | G4: Feasibility analysis requires timely data; delayed or missing data prevents simulation and energy checks. | H4: 859DC-1410-001 HaulX|855DC-1541-DEL Delphi_x000D_ Project - Project Interface_x000D_ Technical-Data/Software_x000D_ This interface provides a near-term forecast of fleet energy consumption. This depends on the HaulX forecast horizon, based on a dispatch plan and mine plan. 30-40% of load based on mobile asset energy consumption. Frequency, resolution and horizon need to be determined for truck and excavator fleet on charge. State of charge, estimated time of completion._x000D_ The criticality level is LOW because, although Delphi receives fleet energy forecasts from HaulX to support planning and optimisation, the interface does not affect real-time haulage operations, safety, or production continuity. If the interface fails, Haulage and mine operations continue normally, though forecast accuracy and decision-making may be reduced. | M4: Draft
A5: GSP-IR-0004 | C5: The interface shall ensure completeness of all mandatory Heavy Mining Equipment (HME) load-profile data fields used by the Eclipse simulation engine. | D5: Interface Requirement | E5: Green Systems Interface Register, Interface DGS-I_0023 | F5: Delphi | G5: Missing fields lead to invalid or failed simulations. | H5: 859DC-1410-001 HaulX|855DC-1541-DEL Delphi_x000D_ Project - Project Interface_x000D_ Technical-Data/Software_x000D_ This interface provides a near-term forecast of fleet energy consumption. This depends on the HaulX forecast horizon, based on a dispatch plan and mine plan. 30-40% of load based on mobile asset energy consumption. Frequency, resolution and horizon need to be determined for truck and excavator fleet on charge. State of charge, estimated time of completion._x000D_ The criticality level is LOW because, although Delphi receives fleet energy forecasts from HaulX to support planning and optimisation, the interface does not affect real-time haulage operations, safety, or production continuity. If the interface fails, Haulage and mine operations continue normally, though forecast accuracy and decision-making may be reduced. | M5: Draft
A6: GSP-IR-0005 | C6: The interface shall ensure integrity of transmitted values, including protection against corruption and preservation of source identifiers and timestamps. | D6: Interface Requirement | E6: Green Systems Interface Register, Interface DGS-I_0023 | F6: Delphi | G6: Compromised integrity produces incorrect feasibility results and curtailment decisions. | H6: 859DC-1410-001 HaulX|855DC-1541-DEL Delphi_x000D_ Project - Project Interface_x000D_ Technical-Data/Software_x000D_ This interface provides a near-term forecast of fleet energy consumption. This depends on the HaulX forecast horizon, based on a dispatch plan and mine plan. 30-40% of load based on mobile asset energy consumption. Frequency, resolution and horizon need to be determined for truck and excavator fleet on charge. State of charge, estimated time of completion._x000D_ The criticality level is LOW because, although Delphi receives fleet energy forecasts from HaulX to support planning and optimisation, the interface does not affect real-time haulage operations, safety, or production continuity. If the interface fails, Haulage and mine operations continue normally, though forecast accuracy and decision-making may be reduced. | M6: Draft
A7: GSP-IR-0006 | C7: The interface shall provide deterministic error handling and clear notifications when Heavy Mining Equipment (HME) data is missing, delayed, or invalid. | D7: Interface Requirement | E7: Green Systems Interface Register, Interface DGS-I_0023 | F7: Delphi | G7: Clear fault visibility is required to avoid silent degradation of planning capability. | H7: 859DC-1410-001 HaulX|855DC-1541-DEL Delphi_x000D_ Project - Project Interface_x000D_ Technical-Data/Software_x000D_ This interface provides a near-term forecast of fleet energy consumption. This depends on the HaulX forecast horizon, based on a dispatch plan and mine plan. 30-40% of load based on mobile asset energy consumption. Frequency, resolution and horizon need to be determined for truck and excavator fleet on charge. State of charge, estimated time of completion._x000D_ The criticality level is LOW because, although Delphi receives fleet energy forecasts from HaulX to support planning and optimisation, the interface does not affect real-time haulage operations, safety, or production continuity. If the interface fails, Haulage and mine operations continue normally, though forecast accuracy and decision-making may be reduced. | M7: Draft
A8: GSP-IR-0007 | C8: The interface shall provide Delphi with continuous access to Snowflake datasets containing historical and actual operational data required for short-term planning. | D8: Interface Requirement | E8: Green Systems Interface Register, Interface DGS-I_0345 | F8: Delphi | G8: Continuous access to historical and actual data is required to support accurate short-term planning; interruptions or gaps degrade forecast quality and decision-making. | H8: 005OP-0000-006 Snowflake (General)|855DC-1541-DEL Delphi_x000D_ Project - Project Interface_x000D_ Technical-Data/Software_x000D_ This interface collects general actuals and historical data residing in Snowflake. Snowflake provides a 'time travel' function, which is from 1 day (default) up to a maximum of 90 days._x000D_ This interface is rated HIGH because accurate historical and actual data underpins short-term forecasting, model validation, and operational planning accuracy. Loss or corruption of this data materially degrades forecast reliability, increasing the risk of incorrect generation dispatch, inefficient curtailment decisions, and potential instability in power management. Reliable historical data is essential for maintaining confidence in optimisation and planning outputs. | M8: Draft
A9: GSP-IR-0008 | C9: The interface shall maintain a minimum availability of 99.9% each calendar month, allowing no more than 43.2 minutes of unplanned downtime per month, to ensure planning and forecasting accuracy is not materially degraded | D9: Interface Requirement | E9: Green Systems Interface Register, Interface DGS-I_0345 | F9: Delphi | G9: Unplanned outages increase the risk of unplanned load curtailment and unsafe conditions. | H9: 005OP-0000-006 Snowflake (General)|855DC-1541-DEL Delphi_x000D_ Project - Project Interface_x000D_ Technical-Data/Software_x000D_ This interface collects general actuals and historical data residing in Snowflake. Snowflake provides a 'time travel' function, which is from 1 day (default) up to a maximum of 90 days._x000D_ This interface is rated HIGH because accurate historical and actual data underpins short-term forecasting, model validation, and operational planning accuracy. Loss or corruption of this data materially degrades forecast reliability, increasing the risk of incorrect generation dispatch, inefficient curtailment decisions, and potential instability in power management. Reliable historical data is essential for maintaining confidence in optimisation and planning outputs. | M9: Draft
A10: GSP-IR-0009 | C10: The interface shall provide version-controlled historical datasets to support consistent retrospective analysis and model training. | D10: Interface Requirement | E10: Green Systems Interface Register, Interface DGS-I_0345 | F10: Delphi | G10: Consistent datasets are needed to reproduce and improve forecasting models. | H10: 005OP-0000-006 Snowflake (General)|855DC-1541-DEL Delphi_x000D_ Project - Project Interface_x000D_ Technical-Data/Software_x000D_ This interface collects general actuals and historical data residing in Snowflake. Snowflake provides a 'time travel' function, which is from 1 day (default) up to a maximum of 90 days._x000D_ This interface is rated HIGH because accurate historical and actual data underpins short-term forecasting, model validation, and operational planning accuracy. Loss or corruption of this data materially degrades forecast reliability, increasing the risk of incorrect generation dispatch, inefficient curtailment decisions, and potential instability in power management. Reliable historical data is essential for maintaining confidence in optimisation and planning outputs. | M10: Draft
A11: GSP-IR-0010 | C11: The interface shall apply data-quality checks, including type, range, and completeness validation, before data is ingested into Delphi. | D11: Interface Requirement | E11: Green Systems Interface Register, Interface DGS-I_0345 | F11: Delphi | G11: Low-quality data can drive unsafe or inefficient planning outcomes. | H11: 005OP-0000-006 Snowflake (General)|855DC-1541-DEL Delphi_x000D_ Project - Project Interface_x000D_ Technical-Data/Software_x000D_ This interface collects general actuals and historical data residing in Snowflake. Snowflake provides a 'time travel' function, which is from 1 day (default) up to a maximum of 90 days._x000D_ This interface is rated HIGH because accurate historical and actual data underpins short-term forecasting, model validation, and operational planning accuracy. Loss or corruption of this data materially degrades forecast reliability, increasing the risk of incorrect generation dispatch, inefficient curtailment decisions, and potential instability in power management. Reliable historical data is essential for maintaining confidence in optimisation and planning outputs. | M11: Draft
A12: GSP-IR-0011 | C12: The interface shall supply real-time operational electrical load data from Ignition SCADA to Delphi for plan-versus-actual calculations. | D12: Interface Requirement | E12: Green Systems Interface Register, Interface DGS-I_0344 | F12: Delphi | G12: Plan-versus-actual comparison requires current load measurements. | H12: 005OP-0000-017 Ignition|855DC-1541-DEL Delphi_x000D_ Project - Project Interface_x000D_ Technical-Data/Software_x000D_ This interface supplies operational data for ground-truth load for plan/forecast vs. actual load calculations._x000D_ This interface is rated HIGH because it provides the authoritative operational load data required to maintain an accurate view of total system demand. Loss, delay, or corruption of this data undermines the integrity of load calculations and forecasting models, increasing the risk of overload conditions, incorrect dispatch or curtailment decisions, and potential safety incidents. Reliable ground-truth data is essential for maintaining power system stability and operational assurance. | M12: Draft
A13: GSP-IR-0012 | C13: The interface shall ensure that SCADA load-data latency does not exceed 2 seconds end-to-end, measured from data capture to availability in the consuming system, to meet the operational threshold required for safe real-time decision-making. | D13: Interface Requirement | E13: Green Systems Interface Register, Interface DGS-I_0344 | F13: Delphi | G13: Excessive latency undermines safe curtailment and control decisions. | H13: 005OP-0000-017 Ignition|855DC-1541-DEL Delphi_x000D_ Project - Project Interface_x000D_ Technical-Data/Software_x000D_ This interface supplies operational data for ground-truth load for plan/forecast vs. actual load calculations._x000D_ This interface is rated HIGH because it provides the authoritative operational load data required to maintain an accurate view of total system demand. Loss, delay, or corruption of this data undermines the integrity of load calculations and forecasting models, increasing the risk of overload conditions, incorrect dispatch or curtailment decisions, and potential safety incidents. Reliable ground-truth data is essential for maintaining power system stability and operational assurance. | M13: Draft
A14: GSP-IR-0013 | C14: The interface shall detect and flag anomalous SCADA load data patterns, including flatlines, spikes, and gaps. | D14: Interface Requirement | E14: Green Systems Interface Register, Interface DGS-I_0344 | F14: Delphi | G14: Anomaly detection reduces the risk of acting on erroneous load information. | H14: 005OP-0000-017 Ignition|855DC-1541-DEL Delphi_x000D_ Project - Project Interface_x000D_ Technical-Data/Software_x000D_ This interface supplies operational data for ground-truth load for plan/forecast vs. actual load calculations._x000D_ This interface is rated HIGH because it provides the authoritative operational load data required to maintain an accurate view of total system demand. Loss, delay, or corruption of this data undermines the integrity of load calculations and forecasting models, increasing the risk of overload conditions, incorrect dispatch or curtailment decisions, and potential safety incidents. Reliable ground-truth data is essential for maintaining power system stability and operational assurance. | M14: Draft
A15: GSP-IR-0014 | C15: The interface shall include metadata, such as timestamps and source identifiers, to support audit and post-event analysis of load data. | D15: Interface Requirement | E15: Green Systems Interface Register, Interface DGS-I_0344 | F15: Delphi | G15: Traceability is required for incident investigation and assurance. | H15: 005OP-0000-017 Ignition|855DC-1541-DEL Delphi_x000D_ Project - Project Interface_x000D_ Technical-Data/Software_x000D_ This interface supplies operational data for ground-truth load for plan/forecast vs. actual load calculations._x000D_ This interface is rated HIGH because it provides the authoritative operational load data required to maintain an accurate view of total system demand. Loss, delay, or corruption of this data undermines the integrity of load calculations and forecasting models, increasing the risk of overload conditions, incorrect dispatch or curtailment decisions, and potential safety incidents. Reliable ground-truth data is essential for maintaining power system stability and operational assurance. | M15: Draft
... A66: GSP-IR-0065 | C66: The interface shall route only aggregated and operationally relevant weather information to the HIVE display, avoiding unnecessary technical detail. | D66: Interface Requirement | E66: Green Systems Interface Register, Interface DGS-I_0213 | F66: Delphi | G66: Operators require concise, actionable information rather than raw data. | H66: Energy Operations (HIVE)|855DC-1541-DEL Delphi_x000D_ Stakeholder - Project Interface_x000D_ Technical-Data/Software_x000D_ Delphi - Aggregated Weather Platform for Actuals & Forecasts (HIVE Display)_x000D_ The purpose of this interface is for Delphi to serve as the central aggregated weather platform, combining actual measured weather data and multiple forecast sources into a single operational view. Energy Operations uses Delphi to monitor real-time and near-term weather conditions - such as wind, irradiance, rainfall, and lightning - via a dedicated display screen in the HIVE control room._x000D_ Intermediate Elements: the Delphi weather aggregation platform, Snowflake datasets, and the HIVE visualisation screen._x000D_ The criticality level is HIGH because reliable, consolidated weather visibility is essential for operational decision-making, forecasting accuracy, and reacting to rapidly changing conditions that affect generation, safety, and dispatch. Failure of this interface causes immediate blindness to changing conditions (e.g., wind gusts or solar drops), risking system instability, inaccurate generation curtailment, or compromising safety protocols (e.g., lightning warnings). | M66: Draft

Sheet Common Data
A2: Artifact Type | B2: Requirement Status | C2: Quality Flaw | D2: Criticality Level | E2: Verification method | F2: Verification Evidence Intent | G2: Verification Evidence Link | H2: Verification Evidence | I2: Verification Justification | J2: Verification Status
A3: Business Requirement | B3: Draft | C3: Untraceable | D3: High | E3: Review | J3: Satisfied
A4: Functional Requirement | B4: Ready for Review | C4: Non‐atomic | D4: Medium | E4: Calculation | J4: Not‐satisfied
A5: System Requirement | B5: Accepted | C5: Ambiguous | D5: Low | E5: Simulation | J5: Partially‐satisfied
A6: Project/Subsystem Requirement | B6: Accepted with Clarification | C6: Duplicate | D6: Very Low | E6: Demonstration
A7: Interface Requirement | B7: Not Accepted | C7: Unverifiable | D7: Unable to Assess | E7: Inspection
A8: Scope Requirement | B8: N/A | C8: Inconsistent | E8: Measurement
A9: Technical Requirement | C9: Unnecessary | E9: Monitoring
A10: Process Requirement | C10: Unattainable | E10: Test
A11: Information | C11: Incomplete | E11: Study
A12: Heading | C12: Multiple Flaws | E12: Analysis
A13: Other | E13: Other

Sheet Requirements Formulas
A1: Req ID | B1: Lvl | C1: Requirement Text | D1: Artifact Type | E1: Source | F1: Apportionment | G1: Rationale | H1: Supporting Information from Interface Register | I1: Criticality Level | J1: Quality Flaw | K1: Verification Method | L1: Validation Method | M1: Requirement Status
A2: {=_xlfn.LET( _xlpm.data,'EA-Fortescue_ReqsImport'!A2:A1000, _xlpm.filtered,_xlfn._xlws.FILTER(_xlpm.data,_xlpm.data<>""), _xlpm.first11,LEFT(_xlpm.filtered,11), _xlpm.last4,VALUE(RIGHT(_xlpm.first11,4)), _xlfn.SORTBY(_xlpm.first11,_xlpm.last4,1) )} -> GSP-RH-0001 | B2: 1 | C2: {=IF(_xlfn.XLOOKUP($A2,LEFT('EA-Fortescue_ReqsImport'!$A:$A,11),'EA-Fortescue_ReqsImport'!R:R)<1,"",_xlfn.XLOOKUP($A2,LEFT('EA-Fortescue_ReqsImport'!$A:$A,11),'EA-Fortescue_ReqsImport'!R:R))} -> Green Systems Interface Requirements | D2: {=IF(_xlfn.XLOOKUP($A2,LEFT('EA-Fortescue_ReqsImport'!$A:$A,11),'EA-Fortescue_ReqsImport'!S:S)<1,"",_xlfn.XLOOKUP($A2,LEFT('EA-Fortescue_ReqsImport'!$A:$A,11),'EA-Fortescue_ReqsImport'!S:S))} -> Heading | E2: {=IF(_xlfn.XLOOKUP($A2,LEFT('EA-Fortescue_ReqsImport'!$A:$A,11),'EA-Fortescue_ReqsImport'!T:T)<1,"",_xlfn.XLOOKUP($A2,LEFT('EA-Fortescue_ReqsImport'!$A:$A,11),'EA-Fortescue_ReqsImport'!T:T))} | F2: {=IF(_xlfn.XLOOKUP($A2,LEFT('EA-Fortescue_ReqsImport'!$A:$A,11),'EA-Fortescue_ReqsImport'!U:U)<1,"",_xlfn.XLOOKUP($A2,LEFT('EA-Fortescue_ReqsImport'!$A:$A,11),'EA-Fortescue_ReqsImport'!U:U))} | G2: {=IF(_xlfn.XLOOKUP($A2,LEFT('EA-Fortescue_ReqsImport'!$A:$A,11),'EA-Fortescue_ReqsImport'!V:V)<1,"",_xlfn.XLOOKUP($A2,LEFT('EA-Fortescue_ReqsImport'!$A:$A,11),'EA-Fortescue_ReqsImport'!V:V))} | H2: {=IF(_xlfn.XLOOKUP($A2,LEFT('EA-Fortescue_ReqsImport'!$A:$A,11),'EA-Fortescue_ReqsImport'!W:W)<1,"",_xlfn.XLOOKUP($A2,LEFT('EA-Fortescue_ReqsImport'!$A:$A,11),'EA-Fortescue_ReqsImport'!W:W))} | M2: {=IF(_xlfn.XLOOKUP($A2,LEFT('EA-Fortescue_ReqsImport'!$A:$A,11),'EA-Fortescue_ReqsImport'!X:X)<1,"N/A",_xlfn.XLOOKUP($A2,LEFT('EA-Fortescue_ReqsImport'!$A:$A,11),'EA-Fortescue_ReqsImport'!X:X))} -> N/A
A3: GSP-RH-0002 | B3: 2 | C3: {=IF(_xlfn.XLOOKUP($A3,LEFT('EA-Fortescue_ReqsImport'!$A:$A,11),'EA-Fortescue_ReqsImport'!R:R)<1,"",_xlfn.XLOOKUP($A3,LEFT('EA-Fortescue_ReqsImport'!$A:$A,11),'EA-Fortescue_ReqsImport'!R:R))} -> Delphi Interface Requirements | D3: {=IF(_xlfn.XLOOKUP($A3,LEFT('EA-Fortescue_ReqsImport'!$A:$A,11),'EA-Fortescue_ReqsImport'!S:S)<1,"",_xlfn.XLOOKUP($A3,LEFT('EA-Fortescue_ReqsImport'!$A:$A,11),'EA-Fortescue_ReqsImport'!S:S))} -> Heading | E3: {=IF(_xlfn.XLOOKUP($A3,LEFT('EA-Fortescue_ReqsImport'!$A:$A,11),'EA-Fortescue_ReqsImport'!T:T)<1,"",_xlfn.XLOOKUP($A3,LEFT('EA-Fortescue_ReqsImport'!$A:$A,11),'EA-Fortescue_ReqsImport'!T:T))} | F3: {=IF(_xlfn.XLOOKUP($A3,LEFT('EA-Fortescue_ReqsImport'!$A:$A,11),'EA-Fortescue_ReqsImport'!U:U)<1,"",_xlfn.XLOOKUP($A3,LEFT('EA-Fortescue_ReqsImport'!$A:$A,11),'EA-Fortescue_ReqsImport'!U:U))} | G3: {=IF(_xlfn.XLOOKUP($A3,LEFT('EA-Fortescue_ReqsImport'!$A:$A,11),'EA-Fortescue_ReqsImport'!V:V)<1,"",_xlfn.XLOOKUP($A3,LEFT('EA-Fortescue_ReqsImport'!$A:$A,11),'EA-Fortescue_ReqsImport'!V:V))} | H3: {=IF(_xlfn.XLOOKUP($A3,LEFT('EA-Fortescue_ReqsImport'!$A:$A,11),'EA-Fortescue_ReqsImport'!W:W)<1,"",_xlfn.XLOOKUP($A3,LEFT('EA-Fortescue_ReqsImport'!$A:$A,11),'EA-Fortescue_ReqsImport'!W:W))} | M3: {=IF(_xlfn.XLOOKUP($A3,LEFT('EA-Fortescue_ReqsImport'!$A:$A,11),'EA-Fortescue_ReqsImport'!X:X)<1,"N/A",_xlfn.XLOOKUP($A3,LEFT('EA-Fortescue_ReqsImport'!$A:$A,11),'EA-Fortescue_ReqsImport'!X:X))} -> N/A
A4: GSP-IR-0003 | C4: {=IF(_xlfn.XLOOKUP($A4,LEFT('EA-Fortescue_ReqsImport'!$A:$A,11),'EA-Fortescue_ReqsImport'!R:R)<1,"",_xlfn.XLOOKUP($A4,LEFT('EA-Fortescue_ReqsImport'!$A:$A,11),'EA-Fortescue_ReqsImport'!R:R))} -> The interface shall provide Heavy Mining Equipment (HME) operational and load-profile input data to Delphi at a frequency of 1 Hz (one update per second), with a maximum end-to-end latency of up to 2 seconds, to support fleet simulation and energy feasibility analysis. | D4: {=IF(_xlfn.XLOOKUP($A4,LEFT('EA-Fortescue_ReqsImport'!$A:$A,11),'EA-Fortescue_ReqsImport'!S:S)<1,"",_xlfn.XLOOKUP($A4,LEFT('EA-Fortescue_ReqsImport'!$A:$A,11),'EA-Fortescue_ReqsImport'!S:S))} -> Interface Requirement | E4: {=IF(_xlfn.XLOOKUP($A4,LEFT('EA-Fortescue_ReqsImport'!$A:$A,11),'EA-Fortescue_ReqsImport'!T:T)<1,"",_xlfn.XLOOKUP($A4,LEFT('EA-Fortescue_ReqsImport'!$A:$A,11),'EA-Fortescue_ReqsImport'!T:T))} -> Green Systems Interface Register, Interface DGS-I_0023 | F4: {=IF(_xlfn.XLOOKUP($A4,LEFT('EA-Fortescue_ReqsImport'!$A:$A,11),'EA-Fortescue_ReqsImport'!U:U)<1,"",_xlfn.XLOOKUP($A4,LEFT('EA-Fortescue_ReqsImport'!$A:$A,11),'EA-Fortescue_ReqsImport'!U:U))} -> Delphi | G4: {=IF(_xlfn.XLOOKUP($A4,LEFT('EA-Fortescue_ReqsImport'!$A:$A,11),'EA-Fortescue_ReqsImport'!V:V)<1,"",_xlfn.XLOOKUP($A4,LEFT('EA-Fortescue_ReqsImport'!$A:$A,11),'EA-Fortescue_ReqsImport'!V:V))} -> Feasibility analysis requires timely data; delayed or missing data prevents simulation and energy checks. | H4: {=IF(_xlfn.XLOOKUP($A4,LEFT('EA-Fortescue_ReqsImport'!$A:$A,11),'EA-Fortescue_ReqsImport'!W:W)<1,"",_xlfn.XLOOKUP($A4,LEFT('EA-Fortescue_ReqsImport'!$A:$A,11),'EA-Fortescue_ReqsImport'!W:W))} -> 859DC-1410-001 HaulX|855DC-1541-DEL Delphi_x000D_ Project - Project Interface_x000D_ Technical-Data/Software_x000D_ This interface provides a near-term forecast of fleet energy consumption. This depends on the HaulX forecast horizon, based on a dispatch plan and mine plan. 30-40% of load based on mobile asset energy consumption. Frequency, resolution and horizon need to be determined for truck and excavator fleet on charge. State of charge, estimated time of completion._x000D_ The criticality level is LOW because, although Delphi receives fleet energy forecasts from HaulX to support planning and optimisation, the interface does not affect real-time haulage operations, safety, or production continuity. If the interface fails, Haulage and mine operations continue normally, though forecast accuracy and decision-making may be reduced. | M4: {=IF(_xlfn.XLOOKUP($A4,LEFT('EA-Fortescue_ReqsImport'!$A:$A,11),'EA-Fortescue_ReqsImport'!X:X)<1,"",_xlfn.XLOOKUP($A4,LEFT('EA-Fortescue_ReqsImport'!$A:$A,11),'EA-Fortescue_ReqsImport'!X:X))} -> Draft
A5: GSP-IR-0004 | C5: {=IF(_xlfn.XLOOKUP($A5,LEFT('EA-Fortescue_ReqsImport'!$A:$A,11),'EA-Fortescue_ReqsImport'!R:R)<1,"",_xlfn.XLOOKUP($A5,LEFT('EA-Fortescue_ReqsImport'!$A:$A,11),'EA-Fortescue_ReqsImport'!R:R))} -> The interface shall ensure completeness of all mandatory Heavy Mining Equipment (HME) load-profile data fields used by the Eclipse simulation engine. | D5: {=IF(_xlfn.XLOOKUP($A5,LEFT('EA-Fortescue_ReqsImport'!$A:$A,11),'EA-Fortescue_ReqsImport'!S:S)<1,"",_xlfn.XLOOKUP($A5,LEFT('EA-Fortescue_ReqsImport'!$A:$A,11),'EA-Fortescue_ReqsImport'!S:S))} -> Interface Requirement | E5: {=IF(_xlfn.XLOOKUP($A5,LEFT('EA-Fortescue_ReqsImport'!$A:$A,11),'EA-Fortescue_ReqsImport'!T:T)<1,"",_xlfn.XLOOKUP($A5,LEFT('EA-Fortescue_ReqsImport'!$A:$A,11),'EA-Fortescue_ReqsImport'!T:T))} -> Green Systems Interface Register, Interface DGS-I_0023 | F5: {=IF(_xlfn.XLOOKUP($A5,LEFT('EA-Fortescue_ReqsImport'!$A:$A,11),'EA-Fortescue_ReqsImport'!U:U)<1,"",_xlfn.XLOOKUP($A5,LEFT('EA-Fortescue_ReqsImport'!$A:$A,11),'EA-Fortescue_ReqsImport'!U:U))} -> Delphi | G5: {=IF(_xlfn.XLOOKUP($A5,LEFT('EA-Fortescue_ReqsImport'!$A:$A,11),'EA-Fortescue_ReqsImport'!V:V)<1,"",_xlfn.XLOOKUP($A5,LEFT('EA-Fortescue_ReqsImport'!$A:$A,11),'EA-Fortescue_ReqsImport'!V:V))} -> Missing fields lead to invalid or failed simulations. | H5: {=IF(_xlfn.XLOOKUP($A5,LEFT('EA-Fortescue_ReqsImport'!$A:$A,11),'EA-Fortescue_ReqsImport'!W:W)<1,"",_xlfn.XLOOKUP($A5,LEFT('EA-Fortescue_ReqsImport'!$A:$A,11),'EA-Fortescue_ReqsImport'!W:W))} -> 859DC-1410-001 HaulX|855DC-1541-DEL Delphi_x000D_ Project - Project Interface_x000D_ Technical-Data/Software_x000D_ This interface provides a near-term forecast of fleet energy consumption. This depends on the HaulX forecast horizon, based on a dispatch plan and mine plan. 30-40% of load based on mobile asset energy consumption. Frequency, resolution and horizon need to be determined for truck and excavator fleet on charge. State of charge, estimated time of completion._x000D_ The criticality level is LOW because, although Delphi receives fleet energy forecasts from HaulX to support planning and optimisation, the interface does not affect real-time haulage operations, safety, or production continuity. If the interface fails, Haulage and mine operations continue normally, though forecast accuracy and decision-making may be reduced. | M5: {=IF(_xlfn.XLOOKUP($A5,LEFT('EA-Fortescue_ReqsImport'!$A:$A,11),'EA-Fortescue_ReqsImport'!X:X)<1,"",_xlfn.XLOOKUP($A5,LEFT('EA-Fortescue_ReqsImport'!$A:$A,11),'EA-Fortescue_ReqsImport'!X:X))} -> Draft
A6: GSP-IR-0005 | C6: {=IF(_xlfn.XLOOKUP($A6,LEFT('EA-Fortescue_ReqsImport'!$A:$A,11),'EA-Fortescue_ReqsImport'!R:R)<1,"",_xlfn.XLOOKUP($A6,LEFT('EA-Fortescue_ReqsImport'!$A:$A,11),'EA-Fortescue_ReqsImport'!R:R))} -> The interface shall ensure integrity of transmitted values, including protection against corruption and preservation of source identifiers and timestamps. | D6: {=IF(_xlfn.XLOOKUP($A6,LEFT('EA-Fortescue_ReqsImport'!$A:$A,11),'EA-Fortescue_ReqsImport'!S:S)<1,"",_xlfn.XLOOKUP($A6,LEFT('EA-Fortescue_ReqsImport'!$A:$A,11),'EA-Fortescue_ReqsImport'!S:S))} -> Interface Requirement | E6: {=IF(_xlfn.XLOOKUP($A6,LEFT('EA-Fortescue_ReqsImport'!$A:$A,11),'EA-Fortescue_ReqsImport'!T:T)<1,"",_xlfn.XLOOKUP($A6,LEFT('EA-Fortescue_ReqsImport'!$A:$A,11),'EA-Fortescue_ReqsImport'!T:T))} -> Green Systems Interface Register, Interface DGS-I_0023 | F6: {=IF(_xlfn.XLOOKUP($A6,LEFT('EA-Fortescue_ReqsImport'!$A:$A,11),'EA-Fortescue_ReqsImport'!U:U)<1,"",_xlfn.XLOOKUP($A6,LEFT('EA-Fortescue_ReqsImport'!$A:$A,11),'EA-Fortescue_ReqsImport'!U:U))} -> Delphi | G6: {=IF(_xlfn.XLOOKUP($A6,LEFT('EA-Fortescue_ReqsImport'!$A:$A,11),'EA-Fortescue_ReqsImport'!V:V)<1,"",_xlfn.XLOOKUP($A6,LEFT('EA-Fortescue_ReqsImport'!$A:$A,11),'EA-Fortescue_ReqsImport'!V:V))} -> Compromised integrity produces incorrect feasibility results and curtailment decisions. | H6: {=IF(_xlfn.XLOOKUP($A6,LEFT('EA-Fortescue_ReqsImport'!$A:$A,11),'EA-Fortescue_ReqsImport'!W:W)<1,"",_xlfn.XLOOKUP($A6,LEFT('EA-Fortescue_ReqsImport'!$A:$A,11),'EA-Fortescue_ReqsImport'!W:W))} -> 859DC-1410-001 HaulX|855DC-1541-DEL Delphi_x000D_ Project - Project Interface_x000D_ Technical-Data/Software_x000D_ This interface provides a near-term forecast of fleet energy consumption. This depends on the HaulX forecast horizon, based on a dispatch plan and mine plan. 30-40% of load based on mobile asset energy consumption. Frequency, resolution and horizon need to be determined for truck and excavator fleet on charge. State of charge, estimated time of completion._x000D_ The criticality level is LOW because, although Delphi receives fleet energy forecasts from HaulX to support planning and optimisation, the interface does not affect real-time haulage operations, safety, or production continuity. If the interface fails, Haulage and mine operations continue normally, though forecast accuracy and decision-making may be reduced. | M6: {=IF(_xlfn.XLOOKUP($A6,LEFT('EA-Fortescue_ReqsImport'!$A:$A,11),'EA-Fortescue_ReqsImport'!X:X)<1,"",_xlfn.XLOOKUP($A6,LEFT('EA-Fortescue_ReqsImport'!$A:$A,11),'EA-Fortescue_ReqsImport'!X:X))} -> Draft
A7: GSP-IR-0006 | C7: {=IF(_xlfn.XLOOKUP($A7,LEFT('EA-Fortescue_ReqsImport'!$A:$A,11),'EA-Fortescue_ReqsImport'!R:R)<1,"",_xlfn.XLOOKUP($A7,LEFT('EA-Fortescue_ReqsImport'!$A:$A,11),'EA-Fortescue_ReqsImport'!R:R))} -> The interface shall provide deterministic error handling and clear notifications when Heavy Mining Equipment (HME) data is missing, delayed, or invalid. | D7: {=IF(_xlfn.XLOOKUP($A7,LEFT('EA-Fortescue_ReqsImport'!$A:$A,11),'EA-Fortescue_ReqsImport'!S:S)<1,"",_xlfn.XLOOKUP($A7,LEFT('EA-Fortescue_ReqsImport'!$A:$A,11),'EA-Fortescue_ReqsImport'!S:S))} -> Interface Requirement | E7: {=IF(_xlfn.XLOOKUP($A7,LEFT('EA-Fortescue_ReqsImport'!$A:$A,11),'EA-Fortescue_ReqsImport'!T:T)<1,"",_xlfn.XLOOKUP($A7,LEFT('EA-Fortescue_ReqsImport'!$A:$A,11),'EA-Fortescue_ReqsImport'!T:T))} -> Green Systems Interface Register, Interface DGS-I_0023 | F7: {=IF(_xlfn.XLOOKUP($A7,LEFT('EA-Fortescue_ReqsImport'!$A:$A,11),'EA-Fortescue_ReqsImport'!U:U)<1,"",_xlfn.XLOOKUP($A7,LEFT('EA-Fortescue_ReqsImport'!$A:$A,11),'EA-Fortescue_ReqsImport'!U:U))} -> Delphi | G7: {=IF(_xlfn.XLOOKUP($A7,LEFT('EA-Fortescue_ReqsImport'!$A:$A,11),'EA-Fortescue_ReqsImport'!V:V)<1,"",_xlfn.XLOOKUP($A7,LEFT('EA-Fortescue_ReqsImport'!$A:$A,11),'EA-Fortescue_ReqsImport'!V:V))} -> Clear fault visibility is required to avoid silent degradation of planning capability. | H7: {=IF(_xlfn.XLOOKUP($A7,LEFT('EA-Fortescue_ReqsImport'!$A:$A,11),'EA-Fortescue_ReqsImport'!W:W)<1,"",_xlfn.XLOOKUP($A7,LEFT('EA-Fortescue_ReqsImport'!$A:$A,11),'EA-Fortescue_ReqsImport'!W:W))} -> 859DC-1410-001 HaulX|855DC-1541-DEL Delphi_x000D_ Project - Project Interface_x000D_ Technical-Data/Software_x000D_ This interface provides a near-term forecast of fleet energy consumption. This depends on the HaulX forecast horizon, based on a dispatch plan and mine plan. 30-40% of load based on mobile asset energy consumption. Frequency, resolution and horizon need to be determined for truck and excavator fleet on charge. State of charge, estimated time of completion._x000D_ The criticality level is LOW because, although Delphi receives fleet energy forecasts from HaulX to support planning and optimisation, the interface does not affect real-time haulage operations, safety, or production continuity. If the interface fails, Haulage and mine operations continue normally, though forecast accuracy and decision-making may be reduced. | M7: {=IF(_xlfn.XLOOKUP($A7,LEFT('EA-Fortescue_ReqsImport'!$A:$A,11),'EA-Fortescue_ReqsImport'!X:X)<1,"",_xlfn.XLOOKUP($A7,LEFT('EA-Fortescue_ReqsImport'!$A:$A,11),'EA-Fortescue_ReqsImport'!X:X))} -> Draft
A8: GSP-IR-0007 | C8: {=IF(_xlfn.XLOOKUP($A8,LEFT('EA-Fortescue_ReqsImport'!$A:$A,11),'EA-Fortescue_ReqsImport'!R:R)<1,"",_xlfn.XLOOKUP($A8,LEFT('EA-Fortescue_ReqsImport'!$A:$A,11),'EA-Fortescue_ReqsImport'!R:R))} -> The interface shall provide Delphi with continuous access to Snowflake datasets containing historical and actual operational data required for short-term planning. | D8: {=IF(_xlfn.XLOOKUP($A8,LEFT('EA-Fortescue_ReqsImport'!$A:$A,11),'EA-Fortescue_ReqsImport'!S:S)<1,"",_xlfn.XLOOKUP($A8,LEFT('EA-Fortescue_ReqsImport'!$A:$A,11),'EA-Fortescue_ReqsImport'!S:S))} -> Interface Requirement | E8: {=IF(_xlfn.XLOOKUP($A8,LEFT('EA-Fortescue_ReqsImport'!$A:$A,11),'EA-Fortescue_ReqsImport'!T:T)<1,"",_xlfn.XLOOKUP($A8,LEFT('EA-Fortescue_ReqsImport'!$A:$A,11),'EA-Fortescue_ReqsImport'!T:T))} -> Green Systems Interface Register, Interface DGS-I_0345 | F8: {=IF(_xlfn.XLOOKUP($A8,LEFT('EA-Fortescue_ReqsImport'!$A:$A,11),'EA-Fortescue_ReqsImport'!U:U)<1,"",_xlfn.XLOOKUP($A8,LEFT('EA-Fortescue_ReqsImport'!$A:$A,11),'EA-Fortescue_ReqsImport'!U:U))} -> Delphi | G8: {=IF(_xlfn.XLOOKUP($A8,LEFT('EA-Fortescue_ReqsImport'!$A:$A,11),'EA-Fortescue_ReqsImport'!V:V)<1,"",_xlfn.XLOOKUP($A8,LEFT('EA-Fortescue_ReqsImport'!$A:$A,11),'EA-Fortescue_ReqsImport'!V:V))} -> Continuous access to historical and actual data is required to support accurate short-term planning; interruptions or gaps degrade forecast quality and decision-making. | H8: {=IF(_xlfn.XLOOKUP($A8,LEFT('EA-Fortescue_ReqsImport'!$A:$A,11),'EA-Fortescue_ReqsImport'!W:W)<1,"",_xlfn.XLOOKUP($A8,LEFT('EA-Fortescue_ReqsImport'!$A:$A,11),'EA-Fortescue_ReqsImport'!W:W))} -> 005OP-0000-006 Snowflake (General)|855DC-1541-DEL Delphi_x000D_ Project - Project Interface_x000D_ Technical-Data/Software_x000D_ This interface collects general actuals and historical data residing in Snowflake. Snowflake provides a 'time travel' function, which is from 1 day (default) up to a maximum of 90 days._x000D_ This interface is rated HIGH because accurate historical and actual data underpins short-term forecasting, model validation, and operational planning accuracy. Loss or corruption of this data materially degrades forecast reliability, increasing the risk of incorrect generation dispatch, inefficient curtailment decisions, and potential instability in power management. Reliable historical data is essential for maintaining confidence in optimisation and planning outputs. | M8: {=IF(_xlfn.XLOOKUP($A8,LEFT('EA-Fortescue_ReqsImport'!$A:$A,11),'EA-Fortescue_ReqsImport'!X:X)<1,"",_xlfn.XLOOKUP($A8,LEFT('EA-Fortescue_ReqsImport'!$A:$A,11),'EA-Fortescue_ReqsImport'!X:X))} -> Draft
A9: GSP-IR-0008 | C9: {=IF(_xlfn.XLOOKUP($A9,LEFT('EA-Fortescue_ReqsImport'!$A:$A,11),'EA-Fortescue_ReqsImport'!R:R)<1,"",_xlfn.XLOOKUP($A9,LEFT('EA-Fortescue_ReqsImport'!$A:$A,11),'EA-Fortescue_ReqsImport'!R:R))} -> The interface shall maintain a minimum availability of 99.9% each calendar month, allowing no more than 43.2 minutes of unplanned downtime per month, to ensure planning and forecasting accuracy is not materially degraded | D9: {=IF(_xlfn.XLOOKUP($A9,LEFT('EA-Fortescue_ReqsImport'!$A:$A,11),'EA-Fortescue_ReqsImport'!S:S)<1,"",_xlfn.XLOOKUP($A9,LEFT('EA-Fortescue_ReqsImport'!$A:$A,11),'EA-Fortescue_ReqsImport'!S:S))} -> Interface Requirement | E9: {=IF(_xlfn.XLOOKUP($A9,LEFT('EA-Fortescue_ReqsImport'!$A:$A,11),'EA-Fortescue_ReqsImport'!T:T)<1,"",_xlfn.XLOOKUP($A9,LEFT('EA-Fortescue_ReqsImport'!$A:$A,11),'EA-Fortescue_ReqsImport'!T:T))} -> Green Systems Interface Register, Interface DGS-I_0345 | F9: {=IF(_xlfn.XLOOKUP($A9,LEFT('EA-Fortescue_ReqsImport'!$A:$A,11),'EA-Fortescue_ReqsImport'!U:U)<1,"",_xlfn.XLOOKUP($A9,LEFT('EA-Fortescue_ReqsImport'!$A:$A,11),'EA-Fortescue_ReqsImport'!U:U))} -> Delphi | G9: {=IF(_xlfn.XLOOKUP($A9,LEFT('EA-Fortescue_ReqsImport'!$A:$A,11),'EA-Fortescue_ReqsImport'!V:V)<1,"",_xlfn.XLOOKUP($A9,LEFT('EA-Fortescue_ReqsImport'!$A:$A,11),'EA-Fortescue_ReqsImport'!V:V))} -> Unplanned outages increase the risk of unplanned load curtailment and unsafe conditions. | H9: {=IF(_xlfn.XLOOKUP($A9,LEFT('EA-Fortescue_ReqsImport'!$A:$A,11),'EA-Fortescue_ReqsImport'!W:W)<1,"",_xlfn.XLOOKUP($A9,LEFT('EA-Fortescue_ReqsImport'!$A:$A,11),'EA-Fortescue_ReqsImport'!W:W))} -> 005OP-0000-006 Snowflake (General)|855DC-1541-DEL Delphi_x000D_ Project - Project Interface_x000D_ Technical-Data/Software_x000D_ This interface collects general actuals and historical data residing in Snowflake. Snowflake provides a 'time travel' function, which is from 1 day (default) up to a maximum of 90 days._x000D_ This interface is rated HIGH because accurate historical and actual data underpins short-term forecasting, model validation, and operational planning accuracy. Loss or corruption of this data materially degrades forecast reliability, increasing the risk of incorrect generation dispatch, inefficient curtailment decisions, and potential instability in power management. Reliable historical data is essential for maintaining confidence in optimisation and planning outputs. | M9: {=IF(_xlfn.XLOOKUP($A9,LEFT('EA-Fortescue_ReqsImport'!$A:$A,11),'EA-Fortescue_ReqsImport'!X:X)<1,"",_xlfn.XLOOKUP($A9,LEFT('EA-Fortescue_ReqsImport'!$A:$A,11),'EA-Fortescue_ReqsImport'!X:X))} -> Draft
A10: GSP-IR-0009 | C10: {=IF(_xlfn.XLOOKUP($A10,LEFT('EA-Fortescue_ReqsImport'!$A:$A,11),'EA-Fortescue_ReqsImport'!R:R)<1,"",_xlfn.XLOOKUP($A10,LEFT('EA-Fortescue_ReqsImport'!$A:$A,11),'EA-Fortescue_ReqsImport'!R:R))} -> The interface shall provide version-controlled historical datasets to support consistent retrospective analysis and model training. | D10: {=IF(_xlfn.XLOOKUP($A10,LEFT('EA-Fortescue_ReqsImport'!$A:$A,11),'EA-Fortescue_ReqsImport'!S:S)<1,"",_xlfn.XLOOKUP($A10,LEFT('EA-Fortescue_ReqsImport'!$A:$A,11),'EA-Fortescue_ReqsImport'!S:S))} -> Interface Requirement | E10: {=IF(_xlfn.XLOOKUP($A10,LEFT('EA-Fortescue_ReqsImport'!$A:$A,11),'EA-Fortescue_ReqsImport'!T:T)<1,"",_xlfn.XLOOKUP($A10,LEFT('EA-Fortescue_ReqsImport'!$A:$A,11),'EA-Fortescue_ReqsImport'!T:T))} -> Green Systems Interface Register, Interface DGS-I_0345 | F10: {=IF(_xlfn.XLOOKUP($A10,LEFT('EA-Fortescue_ReqsImport'!$A:$A,11),'EA-Fortescue_ReqsImport'!U:U)<1,"",_xlfn.XLOOKUP($A10,LEFT('EA-Fortescue_ReqsImport'!$A:$A,11),'EA-Fortescue_ReqsImport'!U:U))} -> Delphi | G10: {=IF(_xlfn.XLOOKUP($A10,LEFT('EA-Fortescue_ReqsImport'!$A:$A,11),'EA-Fortescue_ReqsImport'!V:V)<1,"",_xlfn.XLOOKUP($A10,LEFT('EA-Fortescue_ReqsImport'!$A:$A,11),'EA-Fortescue_ReqsImport'!V:V))} -> Consistent datasets are needed to reproduce and improve forecasting models. | H10: {=IF(_xlfn.XLOOKUP($A10,LEFT('EA-Fortescue_ReqsImport'!$A:$A,11),'EA-Fortescue_ReqsImport'!W:W)<1,"",_xlfn.XLOOKUP($A10,LEFT('EA-Fortescue_ReqsImport'!$A:$A,11),'EA-Fortescue_ReqsImport'!W:W))} -> 005OP-0000-006 Snowflake (General)|855DC-1541-DEL Delphi_x000D_ Project - Project Interface_x000D_ Technical-Data/Software_x000D_ This interface collects general actuals and historical data residing in Snowflake. Snowflake provides a 'time travel' function, which is from 1 day (default) up to a maximum of 90 days._x000D_ This interface is rated HIGH because accurate historical and actual data underpins short-term forecasting, model validation, and operational planning accuracy. Loss or corruption of this data materially degrades forecast reliability, increasing the risk of incorrect generation dispatch, inefficient curtailment decisions, and potential instability in power management. Reliable historical data is essential for maintaining confidence in optimisation and planning outputs. | M10: {=IF(_xlfn.XLOOKUP($A10,LEFT('EA-Fortescue_ReqsImport'!$A:$A,11),'EA-Fortescue_ReqsImport'!X:X)<1,"",_xlfn.XLOOKUP($A10,LEFT('EA-Fortescue_ReqsImport'!$A:$A,11),'EA-Fortescue_ReqsImport'!X:X))} -> Draft
A11: GSP-IR-0010 | C11: {=IF(_xlfn.XLOOKUP($A11,LEFT('EA-Fortescue_ReqsImport'!$A:$A,11),'EA-Fortescue_ReqsImport'!R:R)<1,"",_xlfn.XLOOKUP($A11,LEFT('EA-Fortescue_ReqsImport'!$A:$A,11),'EA-Fortescue_ReqsImport'!R:R))} -> The interface shall apply data-quality checks, including type, range, and completeness validation, before data is ingested into Delphi. | D11: {=IF(_xlfn.XLOOKUP($A11,LEFT('EA-Fortescue_ReqsImport'!$A:$A,11),'EA-Fortescue_ReqsImport'!S:S)<1,"",_xlfn.XLOOKUP($A11,LEFT('EA-Fortescue_ReqsImport'!$A:$A,11),'EA-Fortescue_ReqsImport'!S:S))} -> Interface Requirement | E11: {=IF(_xlfn.XLOOKUP($A11,LEFT('EA-Fortescue_ReqsImport'!$A:$A,11),'EA-Fortescue_ReqsImport'!T:T)<1,"",_xlfn.XLOOKUP($A11,LEFT('EA-Fortescue_ReqsImport'!$A:$A,11),'EA-Fortescue_ReqsImport'!T:T))} -> Green Systems Interface Register, Interface DGS-I_0345 | F11: {=IF(_xlfn.XLOOKUP($A11,LEFT('EA-Fortescue_ReqsImport'!$A:$A,11),'EA-Fortescue_ReqsImport'!U:U)<1,"",_xlfn.XLOOKUP($A11,LEFT('EA-Fortescue_ReqsImport'!$A:$A,11),'EA-Fortescue_ReqsImport'!U:U))} -> Delphi | G11: {=IF(_xlfn.XLOOKUP($A11,LEFT('EA-Fortescue_ReqsImport'!$A:$A,11),'EA-Fortescue_ReqsImport'!V:V)<1,"",_xlfn.XLOOKUP($A11,LEFT('EA-Fortescue_ReqsImport'!$A:$A,11),'EA-Fortescue_ReqsImport'!V:V))} -> Low-quality data can drive unsafe or inefficient planning outcomes. | H11: {=IF(_xlfn.XLOOKUP($A11,LEFT('EA-Fortescue_ReqsImport'!$A:$A,11),'EA-Fortescue_ReqsImport'!W:W)<1,"",_xlfn.XLOOKUP($A11,LEFT('EA-Fortescue_ReqsImport'!$A:$A,11),'EA-Fortescue_ReqsImport'!W:W))} -> 005OP-0000-006 Snowflake (General)|855DC-1541-DEL Delphi_x000D_ Project - Project Interface_x000D_ Technical-Data/Software_x000D_ This interface collects general actuals and historical data residing in Snowflake. Snowflake provides a 'time travel' function, which is from 1 day (default) up to a maximum of 90 days._x000D_ This interface is rated HIGH because accurate historical and actual data underpins short-term forecasting, model validation, and operational planning accuracy. Loss or corruption of this data materially degrades forecast reliability, increasing the risk of incorrect generation dispatch, inefficient curtailment decisions, and potential instability in power management. Reliable historical data is essential for maintaining confidence in optimisation and planning outputs. | M11: {=IF(_xlfn.XLOOKUP($A11,LEFT('EA-Fortescue_ReqsImport'!$A:$A,11),'EA-Fortescue_ReqsImport'!X:X)<1,"",_xlfn.XLOOKUP($A11,LEFT('EA-Fortescue_ReqsImport'!$A:$A,11),'EA-Fortescue_ReqsImport'!X:X))} -> Draft
A12: GSP-IR-0011 | C12: {=IF(_xlfn.XLOOKUP($A12,LEFT('EA-Fortescue_ReqsImport'!$A:$A,11),'EA-Fortescue_ReqsImport'!R:R)<1,"",_xlfn.XLOOKUP($A12,LEFT('EA-Fortescue_ReqsImport'!$A:$A,11),'EA-Fortescue_ReqsImport'!R:R))} -> The interface shall supply real-time operational electrical load data from Ignition SCADA to Delphi for plan-versus-actual calculations. | D12: {=IF(_xlfn.XLOOKUP($A12,LEFT('EA-Fortescue_ReqsImport'!$A:$A,11),'EA-Fortescue_ReqsImport'!S:S)<1,"",_xlfn.XLOOKUP($A12,LEFT('EA-Fortescue_ReqsImport'!$A:$A,11),'EA-Fortescue_ReqsImport'!S:S))} -> Interface Requirement | E12: {=IF(_xlfn.XLOOKUP($A12,LEFT('EA-Fortescue_ReqsImport'!$A:$A,11),'EA-Fortescue_ReqsImport'!T:T)<1,"",_xlfn.XLOOKUP($A12,LEFT('EA-Fortescue_ReqsImport'!$A:$A,11),'EA-Fortescue_ReqsImport'!T:T))} -> Green Systems Interface Register, Interface DGS-I_0344 | F12: {=IF(_xlfn.XLOOKUP($A12,LEFT('EA-Fortescue_ReqsImport'!$A:$A,11),'EA-Fortescue_ReqsImport'!U:U)<1,"",_xlfn.XLOOKUP($A12,LEFT('EA-Fortescue_ReqsImport'!$A:$A,11),'EA-Fortescue_ReqsImport'!U:U))} -> Delphi | G12: {=IF(_xlfn.XLOOKUP($A12,LEFT('EA-Fortescue_ReqsImport'!$A:$A,11),'EA-Fortescue_ReqsImport'!V:V)<1,"",_xlfn.XLOOKUP($A12,LEFT('EA-Fortescue_ReqsImport'!$A:$A,11),'EA-Fortescue_ReqsImport'!V:V))} -> Plan-versus-actual comparison requires current load measurements. | H12: {=IF(_xlfn.XLOOKUP($A12,LEFT('EA-Fortescue_ReqsImport'!$A:$A,11),'EA-Fortescue_ReqsImport'!W:W)<1,"",_xlfn.XLOOKUP($A12,LEFT('EA-Fortescue_ReqsImport'!$A:$A,11),'EA-Fortescue_ReqsImport'!W:W))} -> 005OP-0000-017 Ignition|855DC-1541-DEL Delphi_x000D_ Project - Project Interface_x000D_ Technical-Data/Software_x000D_ This interface supplies operational data for ground-truth load for plan/forecast vs. actual load calculations._x000D_ This interface is rated HIGH because it provides the authoritative operational load data required to maintain an accurate view of total system demand. Loss, delay, or corruption of this data undermines the integrity of load calculations and forecasting models, increasing the risk of overload conditions, incorrect dispatch or curtailment decisions, and potential safety incidents. Reliable ground-truth data is essential for maintaining power system stability and operational assurance. | M12: {=IF(_xlfn.XLOOKUP($A12,LEFT('EA-Fortescue_ReqsImport'!$A:$A,11),'EA-Fortescue_ReqsImport'!X:X)<1,"",_xlfn.XLOOKUP($A12,LEFT('EA-Fortescue_ReqsImport'!$A:$A,11),'EA-Fortescue_ReqsImport'!X:X))} -> Draft
A13: GSP-IR-0012 | C13: {=IF(_xlfn.XLOOKUP($A13,LEFT('EA-Fortescue_ReqsImport'!$A:$A,11),'EA-Fortescue_ReqsImport'!R:R)<1,"",_xlfn.XLOOKUP($A13,LEFT('EA-Fortescue_ReqsImport'!$A:$A,11),'EA-Fortescue_ReqsImport'!R:R))} -> The interface shall ensure that SCADA load-data latency does not exceed 2 seconds end-to-end, measured from data capture to availability in the consuming system, to meet the operational threshold required for safe real-time decision-making. | D13: {=IF(_xlfn.XLOOKUP($A13,LEFT('EA-Fortescue_ReqsImport'!$A:$A,11),'EA-Fortescue_ReqsImport'!S:S)<1,"",_xlfn.XLOOKUP($A13,LEFT('EA-Fortescue_ReqsImport'!$A:$A,11),'EA-Fortescue_ReqsImport'!S:S))} -> Interface Requirement | E13: {=IF(_xlfn.XLOOKUP($A13,LEFT('EA-Fortescue_ReqsImport'!$A:$A,11),'EA-Fortescue_ReqsImport'!T:T)<1,"",_xlfn.XLOOKUP($A13,LEFT('EA-Fortescue_ReqsImport'!$A:$A,11),'EA-Fortescue_ReqsImport'!T:T))} -> Green Systems Interface Register, Interface DGS-I_0344 | F13: {=IF(_xlfn.XLOOKUP($A13,LEFT('EA-Fortescue_ReqsImport'!$A:$A,11),'EA-Fortescue_ReqsImport'!U:U)<1,"",_xlfn.XLOOKUP($A13,LEFT('EA-Fortescue_ReqsImport'!$A:$A,11),'EA-Fortescue_ReqsImport'!U:U))} -> Delphi | G13: {=IF(_xlfn.XLOOKUP($A13,LEFT('EA-Fortescue_ReqsImport'!$A:$A,11),'EA-Fortescue_ReqsImport'!V:V)<1,"",_xlfn.XLOOKUP($A13,LEFT('EA-Fortescue_ReqsImport'!$A:$A,11),'EA-Fortescue_ReqsImport'!V:V))} -> Excessive latency undermines safe curtailment and control decisions. | H13: {=IF(_xlfn.XLOOKUP($A13,LEFT('EA-Fortescue_ReqsImport'!$A:$A,11),'EA-Fortescue_ReqsImport'!W:W)<1,"",_xlfn.XLOOKUP($A13,LEFT('EA-Fortescue_ReqsImport'!$A:$A,11),'EA-Fortescue_ReqsImport'!W:W))} -> 005OP-0000-017 Ignition|855DC-1541-DEL Delphi_x000D_ Project - Project Interface_x000D_ Technical-Data/Software_x000D_ This interface supplies operational data for ground-truth load for plan/forecast vs. actual load calculations._x000D_ This interface is rated HIGH because it provides the authoritative operational load data required to maintain an accurate view of total system demand. Loss, delay, or corruption of this data undermines the integrity of load calculations and forecasting models, increasing the risk of overload conditions, incorrect dispatch or curtailment decisions, and potential safety incidents. Reliable ground-truth data is essential for maintaining power system stability and operational assurance. | M13: {=IF(_xlfn.XLOOKUP($A13,LEFT('EA-Fortescue_ReqsImport'!$A:$A,11),'EA-Fortescue_ReqsImport'!X:X)<1,"",_xlfn.XLOOKUP($A13,LEFT('EA-Fortescue_ReqsImport'!$A:$A,11),'EA-Fortescue_ReqsImport'!X:X))} -> Draft
A14: GSP-IR-0013 | C14: {=IF(_xlfn.XLOOKUP($A14,LEFT('EA-Fortescue_ReqsImport'!$A:$A,11),'EA-Fortescue_ReqsImport'!R:R)<1,"",_xlfn.XLOOKUP($A14,LEFT('EA-Fortescue_ReqsImport'!$A:$A,11),'EA-Fortescue_ReqsImport'!R:R))} -> The interface shall detect and flag anomalous SCADA load data patterns, including flatlines, spikes, and gaps. | D14: {=IF(_xlfn.XLOOKUP($A14,LEFT('EA-Fortescue_ReqsImport'!$A:$A,11),'EA-Fortescue_ReqsImport'!S:S)<1,"",_xlfn.XLOOKUP($A14,LEFT('EA-Fortescue_ReqsImport'!$A:$A,11),'EA-Fortescue_ReqsImport'!S:S))} -> Interface Requirement | E14: {=IF(_xlfn.XLOOKUP($A14,LEFT('EA-Fortescue_ReqsImport'!$A:$A,11),'EA-Fortescue_ReqsImport'!T:T)<1,"",_xlfn.XLOOKUP($A14,LEFT('EA-Fortescue_ReqsImport'!$A:$A,11),'EA-Fortescue_ReqsImport'!T:T))} -> Green Systems Interface Register, Interface DGS-I_0344 | F14: {=IF(_xlfn.XLOOKUP($A14,LEFT('EA-Fortescue_ReqsImport'!$A:$A,11),'EA-Fortescue_ReqsImport'!U:U)<1,"",_xlfn.XLOOKUP($A14,LEFT('EA-Fortescue_ReqsImport'!$A:$A,11),'EA-Fortescue_ReqsImport'!U:U))} -> Delphi | G14: {=IF(_xlfn.XLOOKUP($A14,LEFT('EA-Fortescue_ReqsImport'!$A:$A,11),'EA-Fortescue_ReqsImport'!V:V)<1,"",_xlfn.XLOOKUP($A14,LEFT('EA-Fortescue_ReqsImport'!$A:$A,11),'EA-Fortescue_ReqsImport'!V:V))} -> Anomaly detection reduces the risk of acting on erroneous load information. | H14: {=IF(_xlfn.XLOOKUP($A14,LEFT('EA-Fortescue_ReqsImport'!$A:$A,11),'EA-Fortescue_ReqsImport'!W:W)<1,"",_xlfn.XLOOKUP($A14,LEFT('EA-Fortescue_ReqsImport'!$A:$A,11),'EA-Fortescue_ReqsImport'!W:W))} -> 005OP-0000-017 Ignition|855DC-1541-DEL Delphi_x000D_ Project - Project Interface_x000D_ Technical-Data/Software_x000D_ This interface supplies operational data for ground-truth load for plan/forecast vs. actual load calculations._x000D_ This interface is rated HIGH because it provides the authoritative operational load data required to maintain an accurate view of total system demand. Loss, delay, or corruption of this data undermines the integrity of load calculations and forecasting models, increasing the risk of overload conditions, incorrect dispatch or curtailment decisions, and potential safety incidents. Reliable ground-truth data is essential for maintaining power system stability and operational assurance. | M14: {=IF(_xlfn.XLOOKUP($A14,LEFT('EA-Fortescue_ReqsImport'!$A:$A,11),'EA-Fortescue_ReqsImport'!X:X)<1,"",_xlfn.XLOOKUP($A14,LEFT('EA-Fortescue_ReqsImport'!$A:$A,11),'EA-Fortescue_ReqsImport'!X:X))} -> Draft
A15: GSP-IR-0014 | C15: {=IF(_xlfn.XLOOKUP($A15,LEFT('EA-Fortescue_ReqsImport'!$A:$A,11),'EA-Fortescue_ReqsImport'!R:R)<1,"",_xlfn.XLOOKUP($A15,LEFT('EA-Fortescue_ReqsImport'!$A:$A,11),'EA-Fortescue_ReqsImport'!R:R))} -> The interface shall include metadata, such as timestamps and source identifiers, to support audit and post-event analysis of load data. | D15: {=IF(_xlfn.XLOOKUP($A15,LEFT('EA-Fortescue_ReqsImport'!$A:$A,11),'EA-Fortescue_ReqsImport'!S:S)<1,"",_xlfn.XLOOKUP($A15,LEFT('EA-Fortescue_ReqsImport'!$A:$A,11),'EA-Fortescue_ReqsImport'!S:S))} -> Interface Requirement | E15: {=IF(_xlfn.XLOOKUP($A15,LEFT('EA-Fortescue_ReqsImport'!$A:$A,11),'EA-Fortescue_ReqsImport'!T:T)<1,"",_xlfn.XLOOKUP($A15,LEFT('EA-Fortescue_ReqsImport'!$A:$A,11),'EA-Fortescue_ReqsImport'!T:T))} -> Green Systems Interface Register, Interface DGS-I_0344 | F15: {=IF(_xlfn.XLOOKUP($A15,LEFT('EA-Fortescue_ReqsImport'!$A:$A,11),'EA-Fortescue_ReqsImport'!U:U)<1,"",_xlfn.XLOOKUP($A15,LEFT('EA-Fortescue_ReqsImport'!$A:$A,11),'EA-Fortescue_ReqsImport'!U:U))} -> Delphi | G15: {=IF(_xlfn.XLOOKUP($A15,LEFT('EA-Fortescue_ReqsImport'!$A:$A,11),'EA-Fortescue_ReqsImport'!V:V)<1,"",_xlfn.XLOOKUP($A15,LEFT('EA-Fortescue_ReqsImport'!$A:$A,11),'EA-Fortescue_ReqsImport'!V:V))} -> Traceability is required for incident investigation and assurance. | H15: {=IF(_xlfn.XLOOKUP($A15,LEFT('EA-Fortescue_ReqsImport'!$A:$A,11),'EA-Fortescue_ReqsImport'!W:W)<1,"",_xlfn.XLOOKUP($A15,LEFT('EA-Fortescue_ReqsImport'!$A:$A,11),'EA-Fortescue_ReqsImport'!W:W))} -> 005OP-0000-017 Ignition|855DC-1541-DEL Delphi_x000D_ Project - Project Interface_x000D_ Technical-Data/Software_x000D_ This interface supplies operational data for ground-truth load for plan/forecast vs. actual load calculations._x000D_ This interface is rated HIGH because it provides the authoritative operational load data required to maintain an accurate view of total system demand. Loss, delay, or corruption of this data undermines the integrity of load calculations and forecasting models, increasing the risk of overload conditions, incorrect dispatch or curtailment decisions, and potential safety incidents. Reliable ground-truth data is essential for maintaining power system stability and operational assurance. | M15: {=IF(_xlfn.XLOOKUP($A15,LEFT('EA-Fortescue_ReqsImport'!$A:$A,11),'EA-Fortescue_ReqsImport'!X:X)<1,"",_xlfn.XLOOKUP($A15,LEFT('EA-Fortescue_ReqsImport'!$A:$A,11),'EA-Fortescue_ReqsImport'!X:X))} -> Draft
... A66: GSP-IR-0065 | C66: {=IF(_xlfn.XLOOKUP($A66,LEFT('EA-Fortescue_ReqsImport'!$A:$A,11),'EA-Fortescue_ReqsImport'!R:R)<1,"",_xlfn.XLOOKUP($A66,LEFT('EA-Fortescue_ReqsImport'!$A:$A,11),'EA-Fortescue_ReqsImport'!R:R))} -> The interface shall route only aggregated and operationally relevant weather information to the HIVE display, avoiding unnecessary technical detail. | D66: {=IF(_xlfn.XLOOKUP($A66,LEFT('EA-Fortescue_ReqsImport'!$A:$A,11),'EA-Fortescue_ReqsImport'!S:S)<1,"",_xlfn.XLOOKUP($A66,LEFT('EA-Fortescue_ReqsImport'!$A:$A,11),'EA-Fortescue_ReqsImport'!S:S))} -> Interface Requirement | E66: {=IF(_xlfn.XLOOKUP($A66,LEFT('EA-Fortescue_ReqsImport'!$A:$A,11),'EA-Fortescue_ReqsImport'!T:T)<1,"",_xlfn.XLOOKUP($A66,LEFT('EA-Fortescue_ReqsImport'!$A:$A,11),'EA-Fortescue_ReqsImport'!T:T))} -> Green Systems Interface Register, Interface DGS-I_0213 | F66: {=IF(_xlfn.XLOOKUP($A66,LEFT('EA-Fortescue_ReqsImport'!$A:$A,11),'EA-Fortescue_ReqsImport'!U:U)<1,"",_xlfn.XLOOKUP($A66,LEFT('EA-Fortescue_ReqsImport'!$A:$A,11),'EA-Fortescue_ReqsImport'!U:U))} -> Delphi | G66: {=IF(_xlfn.XLOOKUP($A66,LEFT('EA-Fortescue_ReqsImport'!$A:$A,11),'EA-Fortescue_ReqsImport'!V:V)<1,"",_xlfn.XLOOKUP($A66,LEFT('EA-Fortescue_ReqsImport'!$A:$A,11),'EA-Fortescue_ReqsImport'!V:V))} -> Operators require concise, actionable information rather than raw data. | H66: {=IF(_xlfn.XLOOKUP($A66,LEFT('EA-Fortescue_ReqsImport'!$A:$A,11),'EA-Fortescue_ReqsImport'!W:W)<1,"",_xlfn.XLOOKUP($A66,LEFT('EA-Fortescue_ReqsImport'!$A:$A,11),'EA-Fortescue_ReqsImport'!W:W))} -> Energy Operations (HIVE)|855DC-1541-DEL Delphi_x000D_ Stakeholder - Project Interface_x000D_ Technical-Data/Software_x000D_ Delphi - Aggregated Weather Platform for Actuals & Forecasts (HIVE Display)_x000D_ The purpose of this interface is for Delphi to serve as the central aggregated weather platform, combining actual measured weather data and multiple forecast sources into a single operational view. Energy Operations uses Delphi to monitor real-time and near-term weather conditions - such as wind, irradiance, rainfall, and lightning - via a dedicated display screen in the HIVE control room._x000D_ Intermediate Elements: the Delphi weather aggregation platform, Snowflake datasets, and the HIVE visualisation screen._x000D_ The criticality level is HIGH because reliable, consolidated weather visibility is essential for operational decision-making, forecasting accuracy, and reacting to rapidly changing conditions that affect generation, safety, and dispatch. Failure of this interface causes immediate blindness to changing conditions (e.g., wind gusts or solar drops), risking system instability, inaccurate generation curtailment, or compromising safety protocols (e.g., lightning warnings). | M66: {=IF(_xlfn.XLOOKUP($A66,LEFT('EA-Fortescue_ReqsImport'!$A:$A,11),'EA-Fortescue_ReqsImport'!X:X)<1,"",_xlfn.XLOOKUP($A66,LEFT('EA-Fortescue_ReqsImport'!$A:$A,11),'EA-Fortescue_ReqsImport'!X:X))} -> Draft

Sheet EA-Fortescue_ReqsImport
A1: Name | B1: Type | C1: GUID | D1: Notes | E1: Phase | F1: Version | G1: Stereotype | H1: Fully Qualified Stereotype | I1: Language | J1: Author | K1: Scope | L1: Alias | M1: Status | N1: Keywords | O1: Created Date | P1: Modified Date | Q1: Profile Metatype | R1: TagValue_a. Requirement Text | S1: TagValue_b. Artifact Type | T1: TagValue_c. Source | U1: TagValue_d. Apportionment | V1: TagValue_e. Rationale | W1: TagValue_Supporting information from Interface Register | X1: TagValue_f. Requirement Status | Y1: TagValue_g. Criticality Level | Z1: TagValue_h. Quality Flaw | AA1: TagValue_i. Validation Method | AB1: TagValue_j. Verification Method | AC1: CSV_KEY | AD1: CSV_PARENT_KEY
A2: GSP-RH-0002: Delphi Interface Requirements | B2: Requirement | C2: {AF8A8763-12A0-41c1-81CB-63F83EBA6E1B} | E2: 1 | F2: 1 | G2: requirement | H2: SysML1.4::requirement | I2: <none> | J2: Admin | K2: Public | M2: Draft | O2: 46098.825 | P2: 46099.579 | Q2: SysML1.4::Requirement | R2: Delphi Interface Requirements | S2: Heading | AC2: CSVB0F99EF6 | AD2: CSV03B2E228
A3: GSP-RH-0001: Green Systems Interface Requirements | B3: Requirement | C3: {0FA3DE23-9446-42bc-A097-F6420F5DFA0F} | E3: 1 | F3: 1 | G3: requirement | H3: SysML1.4::requirement | I3: <none> | J3: Admin | K3: Public | M3: Draft | O3: 46098.825 | P3: 46099.579 | Q3: SysML1.4::Requirement | R3: Green Systems Interface Requirements | S3: Heading | AC3: CSV03B2E228
A4: GSP-IR-0018 | B4: Requirement | C4: {F5745D30-2D99-4208-B122-75B98F7B74FE} | E4: 1 | F4: 1 | G4: interfaceRequirement | H4: SysML1.4::interfaceRequirement | I4: <none> | J4: Admin | K4: Public | M4: Draft | O4: 46098.832 | P4: 46099.579 | Q4: SysML1.4::InterfaceRequirement | R4: The interface shall detect and report missing or invalid wind-speed measurements, including out-of-range or non-physical values. | S4: Interface Requirement | T4: Green Systems Interface Register, Interface DGS-I_0331 | U4: Delphi | V4: Detection of bad data prevents corruption of forecast validation results. | W4: 005OP-0000-005-002 Snowflake (Wind)|855DC-1541-DEL Delphi_x000D_ Project - Subsystem Interface_x000D_ Technical-Data/Software_x000D_ Wind Actuals - Field Measurement Data (Multiple Heights)_x000D_ The purpose of this interface is to allow Delphi to collect wind actuals from on-site field instruments, which provide measured wind speeds at multiple heights. Delphi uses this data to validate wind forecasts, support operational decision-making, and improve modelling accuracy for short-term planning._x000D_ The criticality level is HIGH because accurate multi-height wind measurements are essential for validating forecast models and supporting reliable near-term operational planning. Failure compromises modelling accuracy. | X4: Draft | AC4: CSV0539C443 | AD4: CSVB0F99EF6
A5: GSP-IR-0035 | B5: Requirement | C5: {550B5AEB-6338-4d71-8E5A-F13A7C8F0960} | E5: 1 | F5: 1 | G5: interfaceRequirement | H5: SysML1.4::interfaceRequirement | I5: <none> | J5: Admin | K5: Public | M5: Draft | O5: 46098.832 | P5: 46099.579 | Q5: SysML1.4::InterfaceRequirement | R5: The interface shall ingest real-time and historical solar irradiance measurements (W/m2) from the Atevia PI web API for the North Star Junction solar farm into Delphi. | S5: Interface Requirement | T5: Green Systems Interface Register, Interface DGS-I_0329 | U5: Delphi | V5: Actual irradiance is necessary to understand solar resource availability and validate forecasts. | W5: 005OP-0000-005-006 Atevia (Solar NSJ)|855DC-1541-DEL Delphi_x000D_ Project - Subsystem Interface_x000D_ Technical-Data/Software_x000D_ Atevia PI - North Star Junction Solar Irradiance Actuals_x000D_ The purpose of this interface is for Eclipse to consume real-time and historical irradiance (W/m2) measurements provided by the Atevia PI web API from the North Star Junction solar farm. Eclipse uses this data to understand actual solar resource availability, validate forecast performance, and support short-term operational decisions for solar generation and Battery Energy Storage System (BESS) management._x000D_ The criticality level is HIGH because accurate irradiance actuals are essential for near-term operational awareness, forecast validation, and reliable solar generation planning. Failure can compromise short-term operational decisions. | X5: Draft | AC5: CSVAEAD4484 | AD5: CSVB0F99EF6
A6: GSP-IR-0045 | B6: Requirement | C6: {D430BD6F-4CDF-4c7d-8DF5-8DBF558C42ED} | E6: 1 | F6: 1 | G6: interfaceRequirement | H6: SysML1.4::interfaceRequirement | I6: <none> | J6: Admin | K6: Public | M6: Draft | O6: 46098.832 | P6: 46099.579 | Q6: SysML1.4::InterfaceRequirement | R6: The interface shall route Vaisala forecast data through Delphi ingest into Delphi Snowflake in a uni-directional data flow. | S6: Interface Requirement | T6: Green Systems Interface Register, Interface DGS-I_0330 | U6: Delphi | V6: This conforms to the planned data architecture and simplifies governance. | W6: Vaisala|855DC-1541-DEL Delphi_x000D_ External Software - Project Interface_x000D_ Technical-Data/Software_x000D_ Vaisala -Wind Forecast API Integration_x000D_ The purpose of this interface is to allow Delphi to consume the high-resolution wind forecasting provided by Vaisala via API to support short-term operational planning. These forecasts - covering wind speed, direction, and gust information - help operators anticipate generation impacts, manage variability, and adjust site operations proactively._x000D_ The criticality level is HIGH because accurate and timely wind forecasts are essential for maintaining reliable operational planning. Failure risks safety considerations and prevents proactive management of wind-sensitive generation. | X6: Draft | AC6: CSV217EF76F | AD6: CSVB0F99EF6
A7: GSP-IR-0016 | B7: Requirement | C7: {9B5DD6F4-9515-4f1c-B027-555821E73CF1} | E7: 1 | F7: 1 | G7: interfaceRequirement | H7: SysML1.4::interfaceRequirement | I7: <none> | J7: Admin | K7: Public | M7: Draft | O7: 46098.832 | P7: 46099.579 | Q7: SysML1.4::InterfaceRequirement | R7: The interface shall preserve calibration traceability of wind sensors by including identifiers that link measurements to specific field instruments. | S7: Interface Requirement | T7: Green Systems Interface Register, Interface DGS-I_0331 | U7: Delphi | V7: Calibration status must be known to assess confidence in measurements. | W7: 005OP-0000-005-002 Snowflake (Wind)|855DC-1541-DEL Delphi_x000D_ Project - Subsystem Interface_x000D_ Technical-Data/Software_x000D_ Wind Actuals - Field Measurement Data (Multiple Heights)_x000D_ The purpose of this interface is to allow Delphi to collect wind actuals from on-site field instruments, which provide measured wind speeds at multiple heights. Delphi uses this data to validate wind forecasts, support operational decision-making, and improve modelling accuracy for short-term planning._x000D_ The criticality level is HIGH because accurate multi-height wind measurements are essential for validating forecast models and supporting reliable near-term operational planning. Failure compromises modelling accuracy. | X7: Draft | AC7: CSVA818737E | AD7: CSVB0F99EF6
A8: GSP-IR-0012 | B8: Requirement | C8: {21DCB04F-9D25-4121-BE92-FA06152FA354} | E8: 1 | F8: 1 | G8: interfaceRequirement | H8: SysML1.4::interfaceRequirement | I8: <none> | J8: Admin | K8: Public | M8: Draft | O8: 46098.832 | P8: 46099.579 | Q8: SysML1.4::InterfaceRequirement | R8: The interface shall ensure that SCADA load-data latency does not exceed 2 seconds end-to-end, measured from data capture to availability in the consuming system, to meet the operational threshold required for safe real-time decision-making. | S8: Interface Requirement | T8: Green Systems Interface Register, Interface DGS-I_0344 | U8: Delphi | V8: Excessive latency undermines safe curtailment and control decisions. | W8: 005OP-0000-017 Ignition|855DC-1541-DEL Delphi_x000D_ Project - Project Interface_x000D_ Technical-Data/Software_x000D_ This interface supplies operational data for ground-truth load for plan/forecast vs. actual load calculations._x000D_ This interface is rated HIGH because it provides the authoritative operational load data required to maintain an accurate view of total system demand. Loss, delay, or corruption of this data undermines the integrity of load calculations and forecasting models, increasing the risk of overload conditions, incorrect dispatch or curtailment decisions, and potential safety incidents. Reliable ground-truth data is essential for maintaining power system stability and operational assurance. | X8: Draft | AC8: CSV66DD05F3 | AD8: CSVB0F99EF6
A9: GSP-IR-0043 | B9: Requirement | C9: {B8C5A873-AF2A-4919-B858-65D4D4BE397F} | E9: 1 | F9: 1 | G9: interfaceRequirement | H9: SysML1.4::interfaceRequirement | I9: <none> | J9: Admin | K9: Public | M9: Draft | O9: 46098.832 | P9: 46099.579 | Q9: SysML1.4::InterfaceRequirement | R9: The interface shall ingest high-resolution wind speed, direction, and gust forecasts from the Vaisala Wind Forecast API into Delphi via Snowflake. | S9: Interface Requirement | T9: Green Systems Interface Register, Interface DGS-I_0330 | U9: Delphi | V9: These forecasts support short-term operational planning and generation management. | W9: Vaisala|855DC-1541-DEL Delphi_x000D_ External Software - Project Interface_x000D_ Technical-Data/Software_x000D_ Vaisala -Wind Forecast API Integration_x000D_ The purpose of this interface is to allow Delphi to consume the high-resolution wind forecasting provided by Vaisala via API to support short-term operational planning. These forecasts - covering wind speed, direction, and gust information - help operators anticipate generation impacts, manage variability, and adjust site operations proactively._x000D_ The criticality level is HIGH because accurate and timely wind forecasts are essential for maintaining reliable operational planning. Failure risks safety considerations and prevents proactive management of wind-sensitive generation. | X9: Draft | AC9: CSV134F3236 | AD9: CSVB0F99EF6
A10: GSP-IR-0056 | B10: Requirement | C10: {31D0044C-5024-44ac-BABC-0921F4CFAEF0} | E10: 1 | F10: 1 | G10: interfaceRequirement | H10: SysML1.4::interfaceRequirement | I10: <none> | J10: Admin | K10: Public | M10: Draft | O10: 46098.832 | P10: 46099.579 | Q10: SysML1.4::InterfaceRequirement | R10: The interface shall be designed to accommodate a future configuration in which MECO load-forecasting functionality becomes a subsystem of Delphi. | S10: Interface Requirement | T10: Green Systems Interface Register, Interface DGS-I_0005 | U10: Delphi | V10: Forward compatibility reduces rework when roles are consolidated. | W10: 855DC-1541-DEL Delphi|855DC-1543-007 MECO_x000D_ Project - Subsystem Interface_x000D_ _x000D_ Interface Review 25/11/2025: Meco functionality of load forecasting might now be a subsystem of Delphi._x000D_ N/A | X10: Draft | AC10: CSV9E3947CC | AD10: CSVB0F99EF6
A11: GSP-IR-0040 | B11: Requirement | C11: {D5833BA9-7138-4427-AFA9-0F259C66A1D6} | E11: 1 | F11: 1 | G11: interfaceRequirement | H11: SysML1.4::interfaceRequirement | I11: <none> | J11: Admin | K11: Public | M11: Draft | O11: 46098.832 | P11: 46099.579 | Q11: SysML1.4::InterfaceRequirement | R11: The interface shall support short-term planning horizons of at least 48 hours ahead using BOM forecast data. | S11: Interface Requirement | T11: Green Systems Interface Register, Interface DGS-I_0326 | U11: Delphi | V11: The stated planning cycle requires forecasts over this horizon. | W11: BoM|855DC-1541-DEL Delphi_x000D_ External Software - Project Interface_x000D_ Technical-Data/Software_x000D_ Delphi data transfer through Snowflake (BOM API)_x000D_ The purpose of this interface is to provide Eclipse with up-to-date Bureau of Meteorology (BOM) weather forecasts and actuals to support the short-term planning cycle (up to 48 hours ahead) and to build long-term planning models from historical data. This weather data includes wind, solar, rain, and lightning. Additionally, Elysia Battery Energy Storage System (BESS) state of charge (SoC) actuals are provided to Delphi to support operational decisions regarding charging, discharging, and curtailment._x000D_ The criticality level is HIGH because failure to receive timely BOM forecast and actual weather data will cause near- and long-term mine plans to be inaccurate, severely compromising planning feasibility. | X11: Draft | AC11: CSV025EA76A | AD11: CSVB0F99EF6
A12: GSP-IR-0007 | B12: Requirement | C12: {B7A8E43D-37E8-484b-A3DC-7E5C87BAE6B7} | E12: 1 | F12: 1 | G12: interfaceRequirement | H12: SysML1.4::interfaceRequirement | I12: <none> | J12: Admin | K12: Public | M12: Draft | O12: 46098.832 | P12: 46099.579 | Q12: SysML1.4::InterfaceRequirement | R12: The interface shall provide Delphi with continuous access to Snowflake datasets containing historical and actual operational data required for short-term planning. | S12: Interface Requirement | T12: Green Systems Interface Register, Interface DGS-I_0345 | U12: Delphi | V12: Continuous access to historical and actual data is required to support accurate short-term planning; interruptions or gaps degrade forecast quality and decision-making. | W12: 005OP-0000-006 Snowflake (General)|855DC-1541-DEL Delphi_x000D_ Project - Project Interface_x000D_ Technical-Data/Software_x000D_ This interface collects general actuals and historical data residing in Snowflake. Snowflake provides a 'time travel' function, which is from 1 day (default) up to a maximum of 90 days._x000D_ This interface is rated HIGH because accurate historical and actual data underpins short-term forecasting, model validation, and operational planning accuracy. Loss or corruption of this data materially degrades forecast reliability, increasing the risk of incorrect generation dispatch, inefficient curtailment decisions, and potential instability in power management. Reliable historical data is essential for maintaining confidence in optimisation and planning outputs. | X12: Draft | AC12: CSV52ED03E4 | AD12: CSVB0F99EF6
A13: GSP-IR-0054 | B13: Requirement | C13: {C83AD892-0635-4809-A1E0-F7AF75AAED47} | E13: 1 | F13: 1 | G13: interfaceRequirement | H13: SysML1.4::interfaceRequirement | I13: <none> | J13: Admin | K13: Public | M13: Draft | O13: 46098.832 | P13: 46099.579 | Q13: SysML1.4::InterfaceRequirement | R13: The interface shall ensure that SAP work order data is kept consistent with the source SAP database, including handling of updates and closures. | S13: Interface Requirement | T13: Green Systems Interface Register, Interface DGS-I_0004 | U13: Delphi | V13: Consistency is required to avoid mismatches between operational and analytics views. | W13: 005OP-0000-012 SAP|855DC-1541-DEL Delphi_x000D_ Project - Project Interface_x000D_ Technical-Data/Software_x000D_ SAP Work Orders - Equipment Downtime & Maintenance (Snowflake Integration)_x000D_ The purpose of this interface is to surface work order data from SAP in Snowflake so Eclipse can query and understand when in-field equipment (e.g., solar arrays, sensors) is down due to planned or unplanned events. This enables better correlation between asset performance, weather conditions, and operational constraints, including generation outages, planned maintenance, and sensor cleaning._x000D_ Intermediate Elements: Snowflake (storage and query layer for SAP work order and downtime history)._x000D_ The criticality level is HIGH because accurate visibility of equipment downtime is essential for interpreting production impacts and improving forecast accuracy. Failure risks inaccurate energy balance predictions, leading to inefficient generation control. | X13: Draft | AC13: CSV9D9C3923 | AD13: CSVB0F99EF6
A14: GSP-IR-0027 | B14: Requirement | C14: {2518AB8C-2FDB-4675-9BC5-94918166FAB4} | E14: 1 | F14: 1 | G14: interfaceRequirement | H14: SysML1.4::interfaceRequirement | I14: <none> | J14: Admin | K14: Public | M14: Draft | O14: 46098.832 | P14: 46099.579 | Q14: SysML1.4::InterfaceRequirement | R14: The interface shall ingest high-resolution solar irradiance forecasts for the North Star Junction site from the Solstice AI service into Delphi and Eclipse. | S14: Interface Requirement | T14: Green Systems Interface Register, Interface DGS-I_0327 | U14: Delphi | V14: Accurate site-specific irradiance forecasts are required for solar output planning and BESS management. | W14: 005OP-0000-005-004 Solstice|855DC-1541-DEL Delphi_x000D_ Project - Subsystem Interface_x000D_ Technical-Data/Software_x000D_ Solstice AI - North Star Junction Irradiance Forecasting_x000D_ The purpose of this interface is for Solstice AI to provide high-resolution solar irradiance forecasting for the North Star Junction site to support short-term operational decision-making. These forecasts will specifically help operators to anticipate changes in solar generation, adjust dispatch, and manage Battery Energy Storage System (BESS) behaviour proactively._x000D_ The criticality level is HIGH because accurate near-term irradiance forecasts are essential for reliable solar output planning and maintaining stability of site operations. Failure risks incorrect dispatch and management of BESS behaviour. | X14: Draft | AC14: CSV6AEEAB6A | AD14: CSVB0F99EF6
A15: GSP-IR-0062 | B15: Requirement | C15: {BBD49451-2BD5-438d-9BF1-07610C67E24E} | E15: 1 | F15: 1 | G15: interfaceRequirement | H15: SysML1.4::interfaceRequirement | I15: <none> | J15: Admin | K15: Public | M15: Draft | O15: 46098.832 | P15: 46099.579 | Q15: SysML1.4::InterfaceRequirement | R15: The interface shall allow Delphi to present a consolidated operational weather view, combining measured actuals and multiple forecast sources, on the HIVE display for Energy Operations. | S15: Interface Requirement | T15: Green Systems Interface Register, Interface DGS-I_0213 | U15: Delphi | V15: Energy Operations requires a single, integrated weather picture for decision-making. | W15: Energy Operations (HIVE)|855DC-1541-DEL Delphi_x000D_ Stakeholder - Project Interface_x000D_ Technical-Data/Software_x000D_ Delphi - Aggregated Weather Platform for Actuals & Forecasts (HIVE Display)_x000D_ The purpose of this interface is for Delphi to serve as the central aggregated weather platform, combining actual measured weather data and multiple forecast sources into a single operational view. Energy Operations uses Delphi to monitor real-time and near-term weather conditions - such as wind, irradiance, rainfall, and lightning - via a dedicated display screen in the HIVE control room._x000D_ Intermediate Elements: the Delphi weather aggregation platform, Snowflake datasets, and the HIVE visualisation screen._x000D_ The criticality level is HIGH because reliable, consolidated weather visibility is essential for operational decision-making, forecasting accuracy, and reacting to rapidly changing conditions that affect generation, safety, and dispatch. Failure of this interface causes immediate blindness to changing conditions (e.g., wind gusts or solar drops), risking system instability, inaccurate generation curtailment, or compromising safety protocols (e.g., lightning warnings). | X15: Draft | AC15: CSV4BF5FE4C | AD15: CSVB0F99EF6
... A66: GSP-IR-0025 | B66: Requirement | C66: {2A6C7BFE-3460-437f-9410-5F9F506405AD} | E66: 1 | F66: 1 | G66: interfaceRequirement | H66: SysML1.4::interfaceRequirement | I66: <none> | J66: Admin | K66: Public | M66: Proposed | O66: 46098.832 | P66: 46099.579 | Q66: SysML1.4::InterfaceRequirement | R66: The interface shall provide a uni-directional data flow from the Weather Actuals Snowflake dataset into Delphi and Eclipse Snowflake environments. | S66: Interface Requirement | T66: Green Systems Interface Register, Interface DGS-I_0325 | U66: Delphi | V66: Clear, one-way data paths simplify governance and protect source datasets. | W66: 005OP-0000-005-003 Snowflake (Weather)|855DC-1541-DEL Delphi_x000D_ Project - Subsystem Interface_x000D_ Technical-Data/Software_x000D_ Weather Actuals - 15-Year Historical Weather Dataset (Snowflake)_x000D_ The purpose of this interface is to provide up to 15 years of historical weather data - including rain, wind, lightning, and other key variables - via Snowflake through the Weather Actuals system. Eclipse uses this long-term dataset to train and validate forecasting models, analyse historical patterns, and support long-term operational and strategic planning._x000D_ The criticality level is HIGH because a deep and accurate historical weather record is essential for building reliable forecasting models. Failure compromises long-term operational and strategic planning decisions. | X66: Draft | AC66: CSVB09429E6 | AD66: CSVB0F99EF6

Sheet TableDetails
A1: _1588296406066 | B1: <table class="Table" id="_1588296406066" style="border-collapse:collapse; border:solid #d9d9d9 1.0pt; border-collapse : collapse; border-color : #696969;" width="0"> <thead> <tr style="page-break-inside:avoid"> <td colspan="1" id="_1610509710744" rowspan="1" style="background-color:#d3d3d3; background:#d3d3d3 none repeat scroll 0% 0%; border-color:#696969; border-style:none solid solid; border-width:medium 1pt 1pt; height:25px; padding:0cm 5.4pt; text-align:left; vertical-align:middle"><span style="font-size:11pt"><b>PMF Stage</b></span></td> <td colspan="1" id="_1588296406068" rowspan="1" style="background-color:#d3d3d3; background:#d3d3d3 none repeat scroll 0% 0%; border-color:#696969; border-style:none solid solid; border-width:medium 1pt 1pt; height:25px; padding:0cm 5.4pt; text-align:left; vertical-align:middle"> <p id="_1588296406034" style="margin-bottom:8pt; margin-left:0cm; margin-right:0cm; margin-top:0cm"><span style="font-size:11pt"><span style="font-family:Arial,Helvetica,sans-serif"><span style="line-height:107%"><b><span lang="EN-NZ"><span style="line-height:107%">Gate Name</span></span></b></span></span></span></p> </td> <td colspan="1" id="_1588296406069" rowspan="1" style="background-color:#d3d3d3; background:#d3d3d3 none repeat scroll 0% 0%; border-color:#696969; border-style:none solid solid none; border-width:medium 1pt 1pt medium; height:25px; padding:0cm 5.4pt; text-align:left; vertical-align:middle"> <p id="_1588296406035" style="margin-bottom:8pt; margin-left:0cm; margin-right:0cm; margin-top:0cm"><span style="font-size:11pt"><span style="font-family:Arial,Helvetica,sans-serif"><span style="line-height:107%"><b><span lang="EN-NZ"><span style="line-height:107%">Purpose of Stage Gate</span></span></b></span></span></span></p> </td> <td colspan="1" id="_1588296406070" rowspan="1" style="background-color:#d3d3d3; background:#d3d3d3 none repeat scroll 0% 0%; border-color:#696969; border-style:none solid solid none; border-width:medium 1pt 1pt medium; height:25px; padding:0cm 5.4pt; text-align:left; vertical-align:middle"> <p id="_1588296406036" style="margin-bottom:8pt; margin-left:0cm; margin-right:0cm; margin-top:0cm"><span style="font-size:11pt"><span style="font-family:Arial,Helvetica,sans-serif"><span style="line-height:107%"><b><span lang="EN-NZ"><span style="line-height:107%">Engineering Assurance Claim</span></span></b></span></span></span></p> </td> <td colspan="1" id="_1588296406071" rowspan="1" style="background-color:#d3d3d3; background:#d3d3d3 none repeat scroll 0% 0%; border-color:#696969; border-style:none solid solid none; border-width:medium 1pt 1pt medium; height:25px; padding:0cm 5.4pt; text-align:left; vertical-align:middle"> <p id="_1588296406037" style="margin-bottom:8pt; margin-left:0cm; margin-right:0cm; margin-top:0cm"><span style="font-size:11pt"><span style="font-family:Arial,Helvetica,sans-serif"><span style="line-height:107%"><b><span lang="EN-NZ"><span style="line-height:107%">IV Requirement</span></span></b></span></span></span></p> </td> </tr> </thead> <tbody> <tr style="page-break-inside:avoid"> <td colspan="1" id="_1610509710745" rowspan="1" style="border-color:#696969; border-style:none solid solid; border-width:medium 1pt 1pt; height:25px; padding:0cm 5.4pt; text-align:left; vertical-align:middle"><span style="font-size:9pt">3</span></td> <td colspan="1" id="_1588296406072" rowspan="1" style="border-color:#696969; border-style:none solid solid; border-width:medium 1pt 1pt; height:25px; padding:0cm 5.4pt; text-align:left; vertical-align:middle"> <p id="_1588296406038" style="margin-bottom:8pt; margin-left:0cm; margin-right:0cm; margin-top:0cm"><span style="font-family:Arial,Helvetica,sans-serif"><span style="font-size:11pt"><span style="line-height:107%"><span style="font-size:9pt"><span style="line-height:107%">Reference Design</span></span></span></span></span></p> </td> <td colspan="1" id="_1588296406073" rowspan="1" style="border-color:#696969; border-style:none solid solid none; border-width:medium 1pt 1pt medium; height:25px; padding:0cm 5.4pt; text-align:left; vertical-align:middle"> <p id="_1588296406039" style="margin-bottom:8pt; margin-left:0cm; margin-right:0cm; margin-top:0cm"><span style="font-family:Arial,Helvetica,sans-serif"><span style="font-size:11pt"><span style="line-height:107%"><span style="font-size:9pt"><span style="line-height:107%">Project to achieve PMF Stage Gate 3</span></span></span></span></span></p> </td> <td colspan="1" id="_1588296406074" rowspan="1" style="border-color:#696969; border-style:none solid solid none; border-width:medium 1pt 1pt medium; height:25px; padding:0cm 5.4pt; text-align:left; vertical-align:middle"> <p id="_1610508595474" style="margin-bottom:8pt; margin-left:0cm; margin-right:0cm; margin-top:0cm"><span style="font-family:Arial,Helvetica,sans-serif"><span style="font-size:11pt"><span style="line-height:107%"><span style="font-size:9pt"><span style="line-height:107%">Submission shall provide evidence that all requirements of the SWTC have been fulfilled and the design has ensured Safety SFAIRP. </span></span></span></span></span></p> </td> <td colspan="1" id="_1588296406075" rowspan="1" style="border-color:#696969; border-style:none solid solid none; border-width:medium 1pt 1pt medium; height:25px; padding:0cm 5.4pt; text-align:left; vertical-align:middle"> <p id="_1588296406041" style="margin-bottom:8pt; margin-left:0cm; margin-right:0cm; margin-top:0cm"><span style="font-family:Arial,Helvetica,sans-serif"><span style="font-size:11pt"><span style="line-height:107%"><span style="font-size:9pt"><span style="line-height:107%"><span style="background-color:null">Set of IV Certificates that support all Engineering Package Submissions</span></span></span></span></span></span></p> <p id="_1610507338491" style="margin-bottom:8pt; margin-left:0cm; margin-right:0cm; margin-top:0cm"> </p> </td> </tr> <tr style="page-break-inside:avoid"> <td colspan="1" id="_1610509710746" rowspan="1" style="border-color:#696969; border-style:none solid solid; border-width:medium 1pt 1pt; height:25px; padding:0cm 5.4pt; text-align:left; vertical-align:middle"><span style="font-size:9pt">4</span></td> <td colspan="1" id="_1588296406080" rowspan="1" style="border-color:#696969; border-style:none solid solid; border-width:medium 1pt 1pt; height:25px; padding:0cm 5.4pt; text-align:left; vertical-align:middle"> <p id="_1588296406046" style="margin-bottom:8pt; margin-left:0cm; margin-right:0cm; margin-top:0cm"><span style="font-family:Arial,Helvetica,sans-serif"><span style="font-size:11pt"><span style="line-height:107%"><span style="font-size:9pt"><span style="line-height:107%">Detailed Design</span></span></span></span></span></p> </td> <td colspan="1" id="_1588296406081" rowspan="1" style="border-color:#696969; border-style:none solid solid none; border-width:medium 1pt 1pt medium; height:25px; padding:0cm 5.4pt; text-align:left; vertical-align:middle"> <p id="_1588296406047" style="margin-bottom:8pt; margin-left:0cm; margin-right:0cm; margin-top:0cm"><span style="font-family:Arial,Helvetica,sans-serif"><span style="font-size:11pt"><span style="line-height:107%"><span style="font-size:9pt"><span style="line-height:107%">Project to achieve acceptance of the Detailed Design.</span></span></span></span></span></p> </td> <td colspan="1" id="_1588296406082" rowspan="1" style="border-color:#696969; border-style:none solid solid none; border-width:medium 1pt 1pt medium; height:25px; padding:0cm 5.4pt; text-align:left; vertical-align:middle"> <p id="_1588296406048" style="margin-bottom:8pt; margin-left:0cm; margin-right:0cm; margin-top:0cm"><span style="font-family:Arial,Helvetica,sans-serif"><span style="font-size:11pt"><span style="line-height:107%"><span style="font-size:9pt"><span style="line-height:107%">Submission shall evidence all SWTC requirements have been satisfied by detailed design. </span></span></span></span></span></p> </td> <td colspan="1" id="_1588296406083" rowspan="1" style="border-color:#696969; border-style:none solid solid none; border-width:medium 1pt 1pt medium; height:25px; padding:0cm 5.4pt; text-align:left; vertical-align:middle"> <p id="_1588296406049" style="margin-bottom:8pt; margin-left:0cm; margin-right:0cm; margin-top:0cm"><span style="font-family:Arial,Helvetica,sans-serif"><span style="font-size:11pt"><span style="line-height:107%"><span style="font-size:9pt"><span style="line-height:107%"><span style="background-color:null">Set of IV Certificates that support all Engineering Package Submissions</span></span></span></span></span></span></p> </td> </tr> <tr style="page-break-inside:avoid"> <td colspan="1" id="_1610509710747" rowspan="1" style="border-color:#696969; border-style:none solid solid; border-width:medium 1pt 1pt; height:25px; padding:0cm 5.4pt; text-align:left; vertical-align:middle"><span style="font-size:9pt">4</span></td> <td colspan="1" id="_1588296406084" rowspan="1" style="border-color:#696969; border-style:none solid solid; border-width:medium 1pt 1pt; height:25px; padding:0cm 5.4pt; text-align:left; vertical-align:middle"> <p id="_1588296406050" style="margin-bottom:8pt; margin-left:0cm; margin-right:0cm; margin-top:0cm"><span style="font-family:Arial,Helvetica,sans-serif"><span style="font-size:11pt"><span style="line-height:107%"><span style="font-size:9pt"><span style="line-height:107%">IFC</span></span></span></span></span></p> </td> <td colspan="1" id="_1588296406085" rowspan="1" style="border-color:#696969; border-style:none solid solid none; border-width:medium 1pt 1pt medium; height:25px; padding:0cm 5.4pt; text-align:left; vertical-align:middle"> <p id="_1588296406051" style="margin-bottom:8pt; margin-left:0cm; margin-right:0cm; margin-top:0cm"><span style="font-family:Arial,Helvetica,sans-serif"><span style="font-size:11pt"><span style="line-height:107%"><span style="font-size:9pt"><span style="line-height:107%">Project to prove readiness for Construction</span></span></span></span></span></p> <p id="_1610508595476" style="margin-bottom:8pt; margin-left:0cm; margin-right:0cm; margin-top:0cm"><span style="font-family:Arial,Helvetica,sans-serif"><span style="font-size:11pt"><span style="line-height:107%"><span style="font-size:9pt"><span style="line-height:107%">(also achieves PMF Stage 4 design component)</span></span></span></span></span></p> </td> <td colspan="1" id="_1588296406086" rowspan="1" style="border-color:#696969; border-style:none solid solid none; border-width:medium 1pt 1pt medium; height:25px; padding:0cm 5.4pt; text-align:left; vertical-align:middle"> <p id="_1588296406052" style="margin-bottom:8pt; margin-left:0cm; margin-right:0cm; margin-top:0cm"><span style="font-size:9pt"><span style="line-height:107%"><span style="line-height:107%">IFC milestone submission evidences all design comments have been completely closed-out</span></span> and IFC materials have been issued to support Construction and Testing &amp; Commissioning.</span></p> </td> <td colspan="1" id="_1588296406087" rowspan="1" style="border-color:#696969; border-style:none solid solid none; border-width:medium 1pt 1pt medium; height:25px; padding:0cm 5.4pt; text-align:left; vertical-align:middle"> <p id="_1588296406053" style="margin-bottom:8pt; margin-left:0cm; margin-right:0cm; margin-top:0cm"><span style="font-family:Arial,Helvetica,sans-serif"><span style="font-size:11pt"><span style="line-height:107%"><span style="font-size:9pt"><span style="line-height:107%">N/A</span></span></span></span></span></p> </td> </tr> <tr style="page-break-inside:avoid"> <td colspan="1" id="_1610509710748" rowspan="1" style="border-color:#696969; border-style:none solid solid; border-width:medium 1pt 1pt; height:25px; padding:0cm 5.4pt; text-align:left; vertical-align:middle"><span style="font-size:9pt">4</span></td> <td colspan="1" id="_1588296406088" rowspan="1" style="border-color:#696969; border-style:none solid solid; border-width:medium 1pt 1pt; height:25px; padding:0cm 5.4pt; text-align:left; vertical-align:middle"> <p id="_1588296406054" style="margin-bottom:8pt; margin-left:0cm; margin-right:0cm; margin-top:0cm"><span style="font-family:Arial,Helvetica,sans-serif"><span style="font-size:11pt"><span style="line-height:107%"><span style="font-size:9pt"><span style="line-height:107%"><span style="background-color:null">Test and Commissioning </span></span></span></span></span></span></p> </td> <td colspan="1" id="_1588296406089" rowspan="1" style="border-color:#696969; border-style:none solid solid none; border-width:medium 1pt 1pt medium; height:25px; padding:0cm 5.4pt; text-align:left; vertical-align:middle"> <p id="_1588296406055" style="margin-bottom:8pt; margin-left:0cm; margin-right:0cm; margin-top:0cm"><span style="font-family:Arial,Helvetica,sans-serif"><span style="font-size:11pt"><span style="line-height:107%"><span style="font-size:9pt"><span style="line-height:107%"><span style="background-color:null">Project to authorise specific testing and commissioning activities.</span></span></span></span></span></span></p> </td> <td colspan="1" id="_1588296406090" rowspan="1" style="border-color:#696969; border-style:none solid solid none; border-width:medium 1pt 1pt medium; height:25px; padding:0cm 5.4pt; text-align:left; vertical-align:middle"> <p id="_1588296406056" style="margin-bottom:8pt; margin-left:0cm; margin-right:0cm; margin-top:0cm"><span style="font-size:9pt"><span style="font-family:Arial,Helvetica,sans-serif"><span style="line-height:107%"><span style="line-height:107%">Demonstrate readiness to conduct specific high-risk testing and commissioning activities. Evidence is collated that demonstrates the project has ensured safety </span></span>SFAIRP.</span></span></p> </td> <td colspan="1" id="_1588296406091" rowspan="1" style="border-color:#696969; border-style:none solid solid none; border-width:medium 1pt 1pt medium; height:25px; padding:0cm 5.4pt; text-align:left; vertical-align:middle"> <p id="_1588296406057" style="margin-bottom:8pt; margin-left:0cm; margin-right:0cm; margin-top:0cm"><span style="font-family:Arial,Helvetica,sans-serif"><span style="font-size:11pt"><span style="line-height:107%"><span style="font-size:9pt"><span style="line-height:107%"><span style="background-color:null">IV to be applied by PTA discretion</span></span></span></span></span></span></p> </td> </tr> <tr style="page-break-inside:avoid"> <td colspan="1" id="_1610509710749" rowspan="1" style="border-color:#696969; border-style:none solid solid; border-width:medium 1pt 1pt; height:25px; padding:0cm 5.4pt; text-align:left; vertical-align:middle"><span style="font-size:9pt">4</span></td> <td colspan="1" id="_1588296406092" rowspan="1" style="border-color:#696969; border-style:none solid solid; border-width:medium 1pt 1pt; height:25px; padding:0cm 5.4pt; text-align:left; vertical-align:middle"> <p id="_1588296406058" style="margin-bottom:8pt; margin-left:0cm; margin-right:0cm; margin-top:0cm"><span style="font-family:Arial,Helvetica,sans-serif"><span style="font-size:11pt"><span style="line-height:107%"><span style="font-size:9pt"><span style="line-height:107%">Entry into Service (EIS)</span></span></span></span></span></p> </td> <td colspan="1" id="_1588296406093" rowspan="1" style="border-color:#696969; border-style:none solid solid none; border-width:medium 1pt 1pt medium; height:25px; padding:0cm 5.4pt; text-align:left; vertical-align:middle"> <p id="_1588296406059" style="margin-bottom:8pt; margin-left:0cm; margin-right:0cm; margin-top:0cm"><span style="font-family:Arial,Helvetica,sans-serif"><span style="font-size:11pt"><span style="line-height:107%"><span style="font-size:9pt"><span style="line-height:107%">Project to achieve PMF Stage Gate 4</span></span></span></span></span></p> </td> <td colspan="1" id="_1588296406094" rowspan="1" style="border-color:#696969; border-style:none solid solid none; border-width:medium 1pt 1pt medium; height:25px; padding:0cm 5.4pt; text-align:left; vertical-align:middle"> <p id="_1588296406060" style="margin-bottom:8pt; margin-left:0cm; margin-right:0cm; margin-top:0cm"><span style="font-family:Arial,Helvetica,sans-serif"><span style="font-size:11pt"><span style="line-height:107%"><span style="font-size:9pt"><span style="line-height:107%"><span style="background-color:null">Submission shall evidence final As-Constructed and Commissioned deliverables. Safety Case shall demonstrate that the works has ensured safety SFAIRP.</span></span></span></span></span></span></p> <p id="_1610508595477" style="margin-bottom:8pt; margin-left:0cm; margin-right:0cm; margin-top:0cm"><span style="font-family:Arial,Helvetica,sans-serif"><span style="font-size:11pt"><span style="line-height:107%"><span style="font-size:9pt"><span style="line-height:107%">Progressive assurance allows for an element of the works where EIS has been achieved to enter into service, where other elements have not achieved the milestone.</span></span></span></span></span></p> <p id="_1610508595478" style="margin-bottom:8pt; margin-left:0cm; margin-right:0cm; margin-top:0cm"> </p> </td> <td colspan="1" id="_1588296406095" rowspan="1" style="border-color:#696969; border-style:none solid solid none; border-width:medium 1pt 1pt medium; height:25px; padding:0cm 5.4pt; text-align:left; vertical-align:middle"> <p id="_1588296406061" style="margin-bottom:8pt; margin-left:0cm; margin-right:0cm; margin-top:0cm"><span style="font-family:Arial,Helvetica,sans-serif"><span style="font-size:11pt"><span style="line-height:107%"><span style="font-size:9pt"><span style="line-height:107%">Final IV certificate set including all Independent Validation</span></span></span></span></span>.</p> </td> </tr> <tr style="page-break-inside:avoid"> <td colspan="1" id="_1610509710750" rowspan="1" style="border-color:#696969; border-style:none solid solid; border-width:medium 1pt 1pt; height:25px; padding:0cm 5.4pt; text-align:left; vertical-align:middle"><span style="font-size:9pt">5</span></td> <td colspan="1" id="_1588296406096" rowspan="1" style="border-color:#696969; border-style:none solid solid; border-width:medium 1pt 1pt; height:25px; padding:0cm 5.4pt; text-align:left; vertical-align:middle"> <p id="_1588296406062" style="margin-bottom:8pt; margin-left:0cm; margin-right:0cm; margin-top:0cm"><span style="font-family:Arial,Helvetica,sans-serif"><span style="font-size:11pt"><span style="line-height:107%"><span style="font-size:9pt"><span style="line-height:107%">Final Asset Acceptance (FAA)</span></span></span></span></span></p> </td> <td colspan="1" id="_1588296406097" rowspan="1" style="border-color:#696969; border-style:none solid solid none; border-width:medium 1pt 1pt medium; height:25px; padding:0cm 5.4pt; text-align:left; vertical-align:middle"> <p id="_1588296406063" style="margin-bottom:8pt; margin-left:0cm; margin-right:0cm; margin-top:0cm"><span style="font-family:Arial,Helvetica,sans-serif"><span style="font-size:11pt"><span style="line-height:107%"><span style="font-size:9pt"><span style="line-height:107%">Project to achieve PMF Stage Gate 5</span></span></span></span></span></p> </td> <td colspan="1" id="_1588296406098" rowspan="1" style="border-color:#696969; border-style:none solid solid none; border-width:medium 1pt 1pt medium; height:25px; padding:0cm 5.4pt; text-align:left; vertical-align:middle"> <p id="_1588296406064" style="margin-bottom:8pt; margin-left:0cm; margin-right:0cm; margin-top:0cm"><span style="font-family:Arial,Helvetica,sans-serif"><span style="font-size:11pt"><span style="line-height:107%"><span style="font-size:9pt"><span style="line-height:107%">Completion of all project documentation</span></span></span></span></span>.</p> </td> <td colspan="1" id="_1588296406099" rowspan="1" style="border-color:#696969; border-style:none solid solid none; border-width:medium 1pt 1pt medium; height:25px; padding:0cm 5.4pt; text-align:left; vertical-align:middle"> <p id="_1588296406065" style="margin-bottom:8pt; margin-left:0cm; margin-right:0cm; margin-top:0cm"><span style="font-family:Arial,Helvetica,sans-serif"><span style="font-size:11pt"><span style="line-height:107%"><span style="font-size:9pt"><span style="line-height:107%">N/A</span></span></span></span></span></p> </td> </tr> </tbody></table>
A2: _1585121135735 | B2: <table class="Table" dir="ltr" id="_1585121135735" style="border: 1pt solid rgb(105, 105, 105); width: 363px; border-collapse: collapse; border-collapse : collapse; border-color : #696969;" width="0"> <thead> <tr style="page-break-inside:avoid"> <td colspan="1" id="_1583912312659" rowspan="1" style="background-color:#d3d3d3; background:#d3d3d3 none repeat scroll 0% 0%; border-color:#696969; border-style:solid solid solid none; border-width:1pt 1pt 1pt medium; height:25px; padding:0cm 5.4pt; text-align:left; vertical-align:middle; width:110px"> <p id="_1583912312610" style="margin-bottom:8pt; margin-left:0cm; margin-right:0cm; margin-top:0cm"><span style="font-family:Arial,Helvetica,sans-serif"><span style="font-size:11pt"><span style="line-height:107%"><b><span lang="EN-NZ" style="line-height:107%">Site Name</span></b></span></span></span></p> </td> <td colspan="1" id="_1583912312661" rowspan="1" style="background-color:#d3d3d3; background:#d3d3d3 none repeat scroll 0% 0%; border-color:#696969; border-style:solid solid solid none; border-width:1pt 1pt 1pt medium; height:25px; padding:0cm 5.4pt; text-align:left; vertical-align:middle; width:102px"> <p id="_1583912312612" style="margin-bottom:8pt; margin-left:0cm; margin-right:0cm; margin-top:0cm"><span style="font-family:Arial,Helvetica,sans-serif"><span style="font-size:11pt"><span style="line-height:107%"><b><span lang="EN-NZ" style="line-height:107%">Antenna (m)</span></b></span></span></span></p> </td> <td colspan="1" id="_1583912312662" rowspan="1" style="background-color:#d3d3d3; background:#d3d3d3 none repeat scroll 0% 0%; border-color:#696969; border-style:solid solid solid none; border-width:1pt 1pt 1pt medium; height:25px; padding:0cm 5.4pt; text-align:left; vertical-align:middle; width:99px"> <p id="_1583912312613" style="margin-bottom:8pt; margin-left:0cm; margin-right:0cm; margin-top:0cm"><span style="font-family:Arial,Helvetica,sans-serif"><span style="font-size:11pt"><span style="line-height:107%"><b><span lang="EN-NZ" style="line-height:107%">Tower Status</span></b></span></span></span></p> </td> </tr> <tr style="page-break-inside:avoid"> <td colspan="1" id="_1583912312664" rowspan="1" style="border-color:#696969; border-style:none solid solid none; border-width:medium 1pt 1pt medium; height:25px; padding:0cm 5.4pt; text-align:left; vertical-align:middle; width:110px"> <p id="_1583912312615" style="margin-bottom:8pt; margin-left:0cm; margin-right:0cm; margin-top:0cm"><span style="font-family:Arial,Helvetica,sans-serif"><span style="font-size:11pt"><span style="line-height:107%"><span style="font-size:9pt"><span style="line-height:107%">Midland Signalling Building (Arc) Tower</span></span></span></span></span></p> </td> <td colspan="1" id="_1583912312666" rowspan="1" style="border-color:#696969; border-style:none solid solid none; border-width:medium 1pt 1pt medium; height:25px; padding:0cm 5.4pt; text-align:left; vertical-align:middle; width:102px"> <p id="_1583912312617" style="margin-bottom:8pt; margin-left:0cm; margin-right:0cm; margin-top:0cm"><span style="font-family:Arial,Helvetica,sans-serif"><span style="font-size:11pt"><span style="line-height:107%"><span style="font-size:9pt"><span style="line-height:107%">35</span></span></span></span></span></p> </td> <td colspan="1" id="_1583912312667" rowspan="1" style="border-color:#696969; border-style:none solid solid none; border-width:medium 1pt 1pt medium; height:25px; padding:0cm 5.4pt; text-align:left; vertical-align:middle; width:99px"> <p id="_1583912312618" style="margin-bottom:8pt; margin-left:0cm; margin-right:0cm; margin-top:0cm"><span style="font-family:Arial,Helvetica,sans-serif"><span style="font-size:11pt"><span style="line-height:107%"><span style="font-size:9pt"><span style="line-height:107%">Existing</span></span></span></span></span></p> </td> </tr> <tr style="page-break-inside:avoid"> <td colspan="1" id="_1583912312669" rowspan="1" style="border-color:#696969; border-style:none solid solid none; border-width:medium 1pt 1pt medium; height:25px; padding:0cm 5.4pt; text-align:left; vertical-align:middle; width:110px"> <p id="_1583912312621" style="margin-bottom:8pt; margin-left:0cm; margin-right:0cm; margin-top:0cm"><span style="font-family:Arial,Helvetica,sans-serif"><span style="font-size:11pt"><span style="line-height:107%"><span style="font-size:9pt"><span style="line-height:107%">Bellevue Depot (Eastern End)</span></span></span></span></span></p> </td> <td colspan="1" id="_1583912312671" rowspan="1" style="border-color:#696969; border-style:none solid solid none; border-width:medium 1pt 1pt medium; height:25px; padding:0cm 5.4pt; text-align:left; vertical-align:middle; width:102px"> <p id="_1583912312623" style="margin-bottom:8pt; margin-left:0cm; margin-right:0cm; margin-top:0cm"><span style="font-family:Arial,Helvetica,sans-serif"><span style="font-size:9pt">30</span></span></p> </td> <td colspan="1" id="_1583912312672" rowspan="1" style="border-color:#696969; border-style:none solid solid none; border-width:medium 1pt 1pt medium; height:25px; padding:0cm 5.4pt; text-align:left; vertical-align:middle; width:99px"> <p id="_1583912312624" style="margin-bottom:8pt; margin-left:0cm; margin-right:0cm; margin-top:0cm"><span style="font-family:Arial,Helvetica,sans-serif"><span style="font-size:11pt"><span style="line-height:107%"><span style="font-size:9pt"><span style="line-height:107%">New</span></span></span></span></span></p> </td> </tr> </thead></table>
A3: _1585121135735 | B3: <table class="Table" dir="ltr" id="_1585121135735" style="border: 1pt solid rgb(105, 105, 105); width: 231px; border-collapse: collapse; border-collapse : collapse; border-color : #696969;" width="0"> <thead> <tr style="page-break-inside:avoid"> <td colspan="1" id="_1583912312659" rowspan="1" style="background-color:#d3d3d3; background:#d3d3d3 none repeat scroll 0% 0%; border-color:#696969; border-style:solid solid solid none; border-width:1pt 1pt 1pt medium; height:25px; padding:0cm 5.4pt; text-align:left; vertical-align:middle"> <p id="_1583912312610" style="margin-bottom:8pt; margin-left:0cm; margin-right:0cm; margin-top:0cm"><span style="font-family:Arial,Helvetica,sans-serif"><span style="font-size:11pt"><span style="line-height:107%"><b><span lang="EN-NZ" style="line-height:107%">Site Name</span></b></span></span></span></p> </td> <td colspan="1" id="_1583912312662" rowspan="1" style="background-color:#d3d3d3; background:#d3d3d3 none repeat scroll 0% 0%; border-color:#696969; border-style:solid solid solid none; border-width:1pt 1pt 1pt medium; height:25px; padding:0cm 5.4pt; text-align:left; vertical-align:middle; width:85px"> <p id="_1583912312613" style="margin-bottom:8pt; margin-left:0cm; margin-right:0cm; margin-top:0cm"><span style="font-family:Arial,Helvetica,sans-serif"><span style="font-size:11pt"><span style="line-height:107%"><b><span lang="EN-NZ" style="line-height:107%">Site Status</span></b></span></span></span></p> </td> </tr> <tr style="page-break-inside:avoid"> <td colspan="1" id="_1583912312664" rowspan="1" style="border-color:#696969; border-style:none solid solid none; border-width:medium 1pt 1pt medium; height:25px; padding:0cm 5.4pt; text-align:left; vertical-align:middle"> <p id="_1583912312615" style="margin-bottom:8pt; margin-left:0cm; margin-right:0cm; margin-top:0cm"><span style="font-family:Arial,Helvetica,sans-serif"><span style="font-size:11pt"><span style="line-height:107%"><span style="font-size:9pt"><span style="line-height:107%">Midland Multistorey Car Park</span></span></span></span></span></p> </td> <td colspan="1" id="_1583912312667" rowspan="1" style="border-color:#696969; border-style:none solid solid none; border-width:medium 1pt 1pt medium; height:25px; padding:0cm 5.4pt; text-align:left; vertical-align:middle; width:85px"> <p id="_1583912312618" style="margin-bottom:8pt; margin-left:0cm; margin-right:0cm; margin-top:0cm"><span style="font-family:Arial,Helvetica,sans-serif"><span style="font-size:11pt"><span style="line-height:107%"><span style="font-size:9pt"><span style="line-height:107%">New</span></span></span></span></span></p> </td> </tr> <tr style="page-break-inside:avoid"> <td colspan="1" id="_1583912312669" rowspan="1" style="border-color:#696969; border-style:none solid solid none; border-width:medium 1pt 1pt medium; height:25px; padding:0cm 5.4pt; text-align:left; vertical-align:middle"> <p id="_1583912312621" style="margin-bottom:8pt; margin-left:0cm; margin-right:0cm; margin-top:0cm"><span style="font-family:Arial,Helvetica,sans-serif"><span style="font-size:11pt"><span style="line-height:107%"><span style="font-size:9pt"><span style="line-height:107%">Midland Station</span></span></span></span></span></p> </td> <td colspan="1" id="_1583912312672" rowspan="1" style="border-color:#696969; border-style:none solid solid none; border-width:medium 1pt 1pt medium; height:25px; padding:0cm 5.4pt; text-align:left; vertical-align:middle; width:85px"> <p id="_1583912312624" style="margin-bottom:8pt; margin-left:0cm; margin-right:0cm; margin-top:0cm"><span style="font-family:Arial,Helvetica,sans-serif"><span style="font-size:11pt"><span style="line-height:107%"><span style="font-size:9pt"><span style="line-height:107%">New</span></span></span></span></span></p> </td> </tr> </thead></table>
A4: _1568306024508 | B4: <table border="1" cellpadding="0" cellspacing="0" dir="ltr" id="_1568306024508" style="border-color: rgb(105, 105, 105); margin-left: 0px; border-collapse: collapse;"> <tbody> <tr> <th colspan="1" rowspan="1" style="width: 149px; background-color: rgb(211, 211, 211); height: 25px;"> <p dir="ltr" id="_1568306024494" style="margin-left:0px"><b><span style="font-size:11pt"><span style="font-family:Arial,Helvetica,sans-serif"> </span><span style="font-family:Arial,Helvetica,sans-serif">Deliverable Stage</span></span></b></p> </th> <th colspan="1" rowspan="1" style="width: 477px; background-color: rgb(211, 211, 211); height: 25px;"> <p dir="ltr" id="_1568306024495" style="margin-left:0px"><b><span style="font-size:11pt"><span style="font-family:Arial,Helvetica,sans-serif"> </span><span style="font-family:Arial,Helvetica,sans-serif">Deliverables</span></span></b></p> </th> </tr> <tr> <td colspan="1" id="_1568306024509" rowspan="2" style="border-color:#696969; width:149px"> <p dir="ltr" id="_1568306024496" style="margin-left:0px"><span style="font-family:Arial,Helvetica,sans-serif; font-size:9pt"> </span><span style="font-family:Arial,Helvetica,sans-serif; font-size:9pt"><b>Detailed Design</b></span></p> </td> <td colspan="1" id="_1568306024510" rowspan="1" style="border-color:#696969; vertical-align:top; width:477px"> <p dir="ltr" id="_1568306024497" style="margin-left:0px"><span style="font-size:9pt"><span style="font-family:Arial,Helvetica,sans-serif"> </span><span style="font-family:Arial,Helvetica,sans-serif"><b><span lang="EN-AU"><span style="line-height:115%">ESC Interaction Matrix</span></span>: </b><span lang="EN-AU"><span style="line-height:115%">An ESC Interaction Matrix that documents the electromagnetic compatibility of all electrical systems and equipment used in the Works. Where the process identifies any new electrical systems and equipment not previously used within the electrified railway system which are identified as being a high risk of introducing potential electromagnetic disturbances, then the NOP shall prepare an EMC Control Plan and Risk Register for each electrical system or item of equipment considered to be a high risk.</span></span></span></span></p> <p dir="ltr" id="_1568306024498" style="margin-left:0px"><span style="font-size:9pt"><span lang="EN-AU"><span style="line-height:115%"><span style="font-family:&quot;Arial&quot;,sans-serif">T<span style="font-family:Arial,Helvetica,sans-serif">he ESC Interaction Matrix must be prepared during the early Detailed Design phase of the Works and updated on a regular basis throughout the course of the design stages of the Works.</span></span></span></span></span></p> </td> </tr> <tr> <td colspan="1" id="_1568306024511" rowspan="1" style="border-color:#696969; vertical-align:top; width:477px"> <p dir="ltr" id="_1568306024499" style="margin-left:0px"><span style="font-size:9pt"><span style="font-family:Arial,Helvetica,sans-serif"> </span><span style="font-family:Arial,Helvetica,sans-serif"><b><span lang="EN-AU"><span style="line-height:115%">ESC Control Plan and Risk Register</span></span>: </b>Where required, an ESC Control Plan and associated Risk Register that documents the processes to be undertaken in the analysis and recommendations required to ensure ESC issues on the modified electrified rail network are suitably addressed to prevent malfunctioning of any electrical systems and equipment.</span></span></p> <p dir="ltr" id="_1568306705727" style="margin-left:0px"><span style="font-size:9pt"><span lang="EN-AU"><span style="line-height:115%"><span style="font-family:&quot;Arial&quot;,sans-serif"><span style="font-family:Arial,Helvetica,sans-serif">Where required, the ESC Control Plan and associated Risk Register must be prepared during the early Detailed Design phase of the Works and updated on a regular basis throughout the course of the design stages of the Works.</span></span></span></span></span></p> </td> </tr> <tr> <td colspan="1" id="_1568306024512" rowspan="1" style="border-color:#696969; width:149px"> <p dir="ltr" id="_1568306024500" style="margin-left:0px"><span style="font-family:Arial,Helvetica,sans-serif; font-size:9pt"> </span><span style="font-family:Arial,Helvetica,sans-serif; font-size:9pt"><b>Detailed Design <span style="background-color:null">and IFC</span></b></span></p> </td> <td colspan="1" id="_1568306024513" rowspan="1" style="border-color:#696969; vertical-align:top; width:477px"> <p dir="ltr" id="_1568306024501" style="margin-left:0px"><span style="font-size:9pt"><span style="font-family:Arial,Helvetica,sans-serif"> </span><span style="font-family:Arial,Helvetica,sans-serif"><b><span lang="EN-AU"><span style="line-height:115%">ESC Interaction Matrix, Control Plan and Risk Register</span></span>: </b><span lang="EN-AU"><span style="line-height:115%">An updated ESC Interaction Matrix, and where required, Control Plan and Risk Register incorporating any NOP or PTA agreed changes during the later Detailed Design and IFC stages respectively.</span></span></span></span></p> </td> </tr> </tbody></table>
A5: _1566891300923 | B5: <table border="1" cellpadding="0" cellspacing="0" dir="ltr" id="_1566891300923" style="border-color: rgb(105, 105, 105); margin-left: 0px; border-collapse: collapse;"> <tbody> <tr> <th colspan="1" rowspan="1" style="width: 144px; background-color: rgb(211, 211, 211); height: 25px; text-align: left;"> <p dir="ltr" id="_1566891300900" style="margin-left:0px"><span style="font-size:11pt"><b><span style="font-family:Arial,Helvetica,sans-serif">Deliverable Stage</span></b></span></p> </th> <th colspan="1" rowspan="1" style="width: 482px; background-color: rgb(211, 211, 211); height: 25px; text-align: left;"> <p dir="ltr" id="_1566891300901" style="margin-left:0px"><span style="font-size:11pt"><span style="font-family:Arial,Helvetica,sans-serif"> </span><b><span style="font-family:Arial,Helvetica,sans-serif">Deliverables</span></b></span></p> </th> </tr> <tr> <td colspan="1" id="_1566891300924" rowspan="1" style="border-color:#696969; width:144px"> <p dir="ltr" id="_1566891300902" style="margin-left:0px"><span style="font-family:Arial,Helvetica,sans-serif; font-size:9pt"><b>Reference Design</b></span></p> </td> <td colspan="1" id="_1566891300925" rowspan="1" style="border-color:#696969; vertical-align:top; width:482px"> <p dir="ltr" id="_1566891300903" style="margin-left:0px"><span style="font-size:9pt"><span lang="EN-AU"><span style="line-height:115%"><span style="font-family:&quot;Arial&quot;,sans-serif">Electrical hazards and interference methodology associated with the modifications to the electrified rail network shall be mitigated and minimised through the design process, including</span></span></span></span><span style="font-family:Arial,Helvetica,sans-serif; font-size:9pt">:</span></p> <ol dir="ltr" id="_1566891300912" start="1" style="list-style-type:lower-roman"> <li id="_1566891300915" style="margin-left: 0px;"><span style="font-family:Arial,Helvetica,sans-serif; font-size:9pt">Detailed description of how compliance with the SWTC will be achieved by undertaking the following studies and reports:</span> <ol dir="ltr" id="_1566891300913" start="1" style="list-style-type:upper-alpha"> <li id="_1566891300916" style="margin-left: 0px;"><span style="font-family:Arial,Helvetica,sans-serif; font-size:9pt">Electrified Rail Network Investigation and Analysis;</span></li> <li id="_1566891300917" style="margin-left: 0px;"><span style="font-family:Arial,Helvetica,sans-serif; font-size:9pt">Earthing and Bonding strategy;</span></li> <li id="_1568305317925" style="margin-left: 0px;"><span style="font-family:Arial,Helvetica,sans-serif; font-size:9pt">Earthing and Bonding verification; and</span></li> <li id="_1568305317926" style="margin-left: 0px;"><span style="font-family:Arial,Helvetica,sans-serif; font-size:9pt">Earthing and Bonding acceptance.</span></li> </ol> </li> <li id="_1566891300918" style="margin-left: 0px;"><span style="font-family:Arial,Helvetica,sans-serif; font-size:9pt">Description of key philosophies and major constraints in the identification, assessment and mitigation of any HV electrical hazards and interference works.</span></li> <li id="_1566891300919" style="margin-left: 0px;"><span style="font-family:Arial,Helvetica,sans-serif; font-size:9pt">Description of any identified major non-compliances to the HV electrical hazards and interference works.</span></li> <li id="_1566891300920" style="margin-left: 0px;"><span style="font-family:Arial,Helvetica,sans-serif; font-size:9pt">Description of any identified major design risks associated with the HV electrical hazards and interference works.</span></li> </ol> </td> </tr> <tr> <td colspan="1" id="_1566891300926" rowspan="2" style="border-color:#696969; width:144px"> <p dir="ltr" id="_1566891300904" style="margin-left:0px"><span style="font-family:Arial,Helvetica,sans-serif; font-size:9pt"><b>Early Detailed Design</b></span></p> </td> <td colspan="1" id="_1566891300927" rowspan="1" style="border-color:#696969; vertical-align:top; width:482px"> <p dir="ltr" id="_1566891300905" style="margin-left:0px"><span style="font-size:9pt"><span style="font-family:Arial,Helvetica,sans-serif"><b>Electrified Rail Network Investigation and Analysis: </b>An investigation and analysis Report that summarises the processes to be undertaken in the investigation, analysis and recommendations required to ensure potential HV electrical hazards and interference on the modified electrified rail network are maintained at a safe level prescribed by PTA’s Earthing and Bonding Specification and prevent malfunctioning of all railway systems and equipment. </span><span lang="EN-AU"><span style="line-height:115%"><span style="font-family:&quot;Arial&quot;,sans-serif">The Report must also consider any potential issues associated with the existing Western Power 132kV AC aerial transmission line.</span></span></span></span></p> <p dir="ltr" id="_1568305317924" style="margin-left:0px"><span style="font-size:9pt"><span lang="EN-AU"><span style="line-height:115%"><span style="font-family:&quot;Arial&quot;,sans-serif">The investigation and analysis Report must be prepared during the early Detailed Design phase of the Works and updated on a regular basis throughout the course of the design stages of the Works.</span></span></span></span></p> </td> </tr> <tr> <td colspan="1" id="_1566891300928" rowspan="1" style="border-color:#696969; vertical-align:top; width:482px"> <p dir="ltr" id="_1566891300906" style="margin-left:0px"><span style="font-size:9pt"><span style="font-family:Arial,Helvetica,sans-serif"><b>Earthing and Bonding Strategy: </b></span><span lang="EN-AU"><span style="line-height:115%"><span style="font-family:&quot;Arial&quot;,sans-serif">An Earthing and Bonding Strategy Report that documents the proposed Earthing and Bonding strategy to be implemented for the Midland Station and all associated Rail Infrastructure Works. The strategy Report must be prepared during the early Detailed Design phase of the Works and updated on a regular basis throughout the course of the design stages of the Works</span></span></span><span style="font-family:Arial,Helvetica,sans-serif">.</span></span></p> </td> </tr> <tr> <td colspan="1" id="_1566891300929" rowspan="2" style="border-color:#696969; width:144px"> <p dir="ltr" id="_1566891300907" style="margin-left:0px"><span style="font-family:Arial,Helvetica,sans-serif; font-size:9pt"><b>Detailed Design </b></span></p> </td> <td colspan="1" id="_1566891300930" rowspan="1" style="border-color:#696969; vertical-align:top; width:482px"> <p dir="ltr" id="_1566891300908" style="margin-left:0px"><span style="font-size:9pt"><span style="font-family:Arial,Helvetica,sans-serif"><b>Electrified Rail Network Investigation and Analysis: </b></span><span lang="EN-AU"><span style="line-height:115%"><span style="font-family:&quot;Arial&quot;,sans-serif">An updated investigation and analysis Report incorporating any Alliance or PTA agreed changes during the late Detailed Design and IFC stages respectively</span></span></span><span style="font-family:Arial,Helvetica,sans-serif">.</span></span></p> </td> </tr> <tr> <td colspan="1" id="_1566891300931" rowspan="1" style="border-color:#696969; vertical-align:top; width:482px"> <p dir="ltr" id="_1566891300909" style="margin-left:0px"><span style="font-size:9pt"><span style="font-family:Arial,Helvetica,sans-serif"><b>Earthing and Bonding Strategy: </b></span><span lang="EN-AU"><span style="line-height:115%"><span style="font-family:&quot;Arial&quot;,sans-serif">An updated Earthing and Bonding Strategy Report incorporating any Alliance or PTA agreed changes during the Developed and late Detailed Design and IFC stages respectively</span></span></span><span style="font-family:Arial,Helvetica,sans-serif">.</span></span></p> </td> </tr> <tr> <td colspan="1" id="_1566891300932" rowspan="1" style="border-color:#696969; width:144px"> <p dir="ltr" id="_1566891300910" style="margin-left:0px"><span style="font-family:Arial,Helvetica,sans-serif; font-size:9pt"><b>Construction and Acceptance</b></span></p> </td> <td colspan="1" id="_1566891300933" rowspan="1" style="border-color:#696969; vertical-align:top; width:482px"> <p dir="ltr" id="_1566891300911" style="margin-left:0px"><span style="font-size:9pt"><span lang="EN-AU"><span style="line-height:115%"><span style="font-family:&quot;Arial&quot;,sans-serif">Provide all obligatory construction and Acceptance deliverables for the HV electrical hazards and interference works required to be provided for the Midland Station and all associated Rail Infrastructure Works in accordance with the PTA procedures, specifications and in particular PTA’s Earthing and Bonding Specification, including</span></span></span><span style="font-family:Arial,Helvetica,sans-serif">:</span></span></p> <ol dir="ltr" id="_1566891300914" start="1" style="list-style-type:lower-roman"> <li id="_1566891300921" style="margin-left: 0px;"><span style="font-size:9pt"><span style="font-family:Arial,Helvetica,sans-serif">An Earthing and Bonding Verification Testing Report; and</span></span></li> <li id="_1566891300922" style="margin-left: 0px;"><span style="font-size:9pt"><span style="font-family:Arial,Helvetica,sans-serif">An Earthing and Bonding Acceptance Report.</span></span></li> </ol> </td> </tr> </tbody></table>
